Workbook

Sheet Strategy & Legend
B2: 2026 Draft Cheat Sheet — ESPN: FE Fantasy Football (Full PPR / 1.0 per reception) — news refreshed Sept 3, 2026
B6: YOUR LEAGUE
B7: Head-to-Head Points, FULL-PPR (1.0/rec). Pass 0.04/yd (1/25), Pass TD 4, INT -2. Rush 0.1/yd (1/10), TD 6. Rec 0.1/yd (1/10), Reception 1.0, TD 6. Fumble lost -2, 2pt 2, Return TD 6. Kicker uses distance scoring + miss penalties; D/ST uses points-allowed AND yards-allowed tiers (see the 'ESPN Scoring' tab). DRAFT: 16 rounds = 16 roster spots per team (~7 bench behind your starters). Exact STARTING slots (QB count, FLEX count, any Superflex) still aren't in the exported PDF — confirm them in League Settings > Basic Settings, since a Superflex/2QB build would move QBs up sharply.
B9: INJURY / SUSPENSION FLAGS (new)
B10: The 'Flag' column marks players with reported injury or suspension concerns. Injury/suspension detail was refreshed Sept 3, 2026 (ESPN, Yahoo Sports, SI, FantasyPros, Sharp Football, NBC/PFT). Red name cell = likely to miss time / real risk; Yellow = monitor / playing through; Green = a cloud that's been cleared (e.g., Rashee Rice). Full detail + draft impact is on the 'Injury & Susp. Watch' tab.
B11: IMPORTANT: only players with reported concerns are flagged — an unflagged player is NOT confirmed healthy, just not in the news as of Sept 3. Injuries and suspensions move daily; re-check again the morning of your draft (see the Sleeper live-status note below).
B12: SUSPENSION/AVAILABILITY (as of Sept 3): Josh Jacobs is ON the commissioner's exempt list (Aug 30) — out indefinitely to start the season. Puka Nacua is NOT on the exempt list and has no announced suspension — likely plays Wk1. Rashee Rice was CLEARED (NFL closed its investigation in April 2026, no discipline).
B14: VALUE / ADP RE-ANCHOR
B15: Board ordered by fresh market ADP (FFC 12-team, 2,828 mocks Aug 17-22) and an Aug-9 expert board. 'Mkt Rk' = market order; 'Exp Rk' = expert board. Value = Mkt Rk - Exp Rk (green = experts higher than market = possible discount; red = fade/riser). CAVEAT: this ADP was sampled from HALF-PPR mocks. In your FULL-PPR league, WR/TE and pass-catching RBs drift up a few spots vs. what ADP shows here — treat ADP as directional, and lean toward receptions on close calls (see the 'PPR Lean' column).
B16: 'Verdict' flags UNDERVALUED (green) / OVERVALUED (red) / Fair. 'Rec Rd' = recommended round to target — a blend of the expert and market ranks, pushed a round later for injury/suspension risk. Don't reach much earlier than Rec Rd; for undervalued players you can often wait toward their ADP round.
B18: BYE-CONFLICT CHECKER (tab: My Team + Byes)
B19: Pick players from the dropdown; Pos/Team/Bye/Status auto-fill. Mark Starter?=Y. The table flags any week where 2+ starters at the same position share a bye or 3+ starters are out. K/DST aren't on the board — enter their byes manually if you want them counted.
... B52: • Gray / white row banding = draft-round grouping (color flips each round).

Sheet ESPN Scoring
B2: ESPN Scoring — FE Fantasy Football
B3: Transcribed from your exported League Settings > Scoring page (ESPN, 9/3/2026). Lineup/roster slots were not on that page — confirm them in Basic Settings.
B5: Category | C5: Pts | D5: Notes
B6: PASSING
B7: Passing Yards (PY) | C7: 0.04 | D7: 1 point per 25 passing yards
B8: TD Pass (PTD) | C8: 4
B9: Interception Thrown (INT) | C9: -2 | D9: Yahoo used -1 — slightly harsher on turnover-prone QBs
B10: 2pt Passing Conversion (2PC) | C10: 2
B12: RUSHING
B13: Rushing Yards (RY) | C13: 0.1 | D13: 1 point per 10 rushing yards
B14: TD Rush (RTD) | C14: 6
B15: 2pt Rushing Conversion (2PR) | C15: 2
B17: RECEIVING (FULL PPR)
B18: Each Reception (REC) | C18: 1 | D18: FULL PPR — receptions worth 2x the Half-PPR board's assumption
B19: Receiving Yards (REY) | C19: 0.1 | D19: 1 point per 10 receiving yards
B20: TD Reception (RETD) | C20: 6
B21: 2pt Receiving Conversion (2PRE) | C21: 2
B23: KICKING
B24: PAT Made (PAT) | C24: 1
B25: PAT Missed (PATM) | C25: -2 | D25: Penalty for misses — value accuracy
B26: FG Missed, total (FGM) | C26: -1 | D26: Penalty for misses — value accuracy
B27: FG Made 0-39 yds (FG0) | C27: 3
B28: FG Made 40-49 yds (FG40) | C28: 4
B29: FG Made 50-59 yds (FG50) | C29: 5
B30: FG Made 60+ yds (FG60) | C30: 6 | D30: Big-leg kickers gain the most
B32: DEFENSE / SPECIAL TEAMS
B33: Each Sack (SK) | C33: 1
B34: Each Interception (INT) | C34: 2
B35: Each Fumble Recovered (FR) | C35: 2
B36: Each Safety (SF) | C36: 2
B37: Blocked Punt/PAT/FG (BLKK) | C37: 2
B38: Def/ST TD (INT, Fum, KR, PR, Blk return) | C38: 6 | D38: All return & defensive TDs
B39: 2pt Return (2PTRET) | C39: 2
B40: 1pt Safety (1PSF) | C40: 1
B42: D/ST — POINTS ALLOWED (per game)
B43: 0 points | C43: 5
B44: 1-6 | C44: 4
B45: 7-13 | C45: 3
B46: 14-17 | C46: 1
B47: 18-27 (implied) | C47: 0
B48: 28-34 | C48: -1
B49: 35-45 | C49: -3
B50: 46+ | C50: -5
B52: D/ST — TOTAL YARDS ALLOWED (per game)
B53: < 100 yds | C53: 5
B54: 100-199 | C54: 3
B55: 200-299 | C55: 2
B56: 300-349 (implied) | C56: 0
B57: 350-399 | C57: -1
B58: 400-449 | C58: -3
B59: 450-499 | C59: -5
B60: 500-549 | C60: -6
B61: 550+ | C61: -7
B63: MISCELLANEOUS / TURNOVERS
B64: Fumble Lost (FUML) — offensive players | C64: -2

Sheet My Team + Byes
A1: MY TEAM — auto-fills from column A on the Draft Board (set a player to ★)
A2: Column A: ☐ available · ☑ drafted by another team · ★ my pick. Set ★ to add a player here (K/DST included). Bye counts (right) cover QB/RB/WR/TE.
A3: Players on my team: | B3: =COUNTIF('Draft Board'!$A$3:$A$180,"★") -> 0 | H3: BYE-WEEK LOAD (my players)
A4: Player | B4: Pos | C4: Team | D4: Bye | E4: Status | H4: Bye Wk | I4: QB | J4: RB | K4: WR | L4: TE | M4: My Players | N4: Conflict
A5: =IFERROR(__xludf.dummyfunction("IFERROR(sort(filter({'Draft Board'!D2:D179,'Draft Board'!E2:E179,'Draft Board'!G2:G179,'Draft Board'!H2:H179,'Draft Board'!M2:M179},'Draft Board'!A2:A179=""★""),2,TRUE()),""— no players set to ★ yet —"")"),"— no players set to ★ yet —") -> — no players set to ★ yet — | H5: 5 | I5: =COUNTIFS('Draft Board'!$A$3:$A$180,"★",'Draft Board'!$E$3:$E$180,"QB",'Draft Board'!$H$3:$H$180,$H5) -> 0 | J5: =COUNTIFS('Draft Board'!$A$3:$A$180,"★",'Draft Board'!$E$3:$E$180,"RB",'Draft Board'!$H$3:$H$180,$H5) -> 0 | K5: =COUNTIFS('Draft Board'!$A$3:$A$180,"★",'Draft Board'!$E$3:$E$180,"WR",'Draft Board'!$H$3:$H$180,$H5) -> 0 | L5: =COUNTIFS('Draft Board'!$A$3:$A$180,"★",'Draft Board'!$E$3:$E$180,"TE",'Draft Board'!$H$3:$H$180,$H5) -> 0 | M5: =SUM(I5:L5) -> 0 | N5: =IF(OR(J5>=2,K5>=2),"⚠ 2+ same position",IF(M5>=3,"Heavy week",""))
H6: 6 | I6: =COUNTIFS('Draft Board'!$A$3:$A$180,"★",'Draft Board'!$E$3:$E$180,"QB",'Draft Board'!$H$3:$H$180,$H6) -> 0 | J6: =COUNTIFS('Draft Board'!$A$3:$A$180,"★",'Draft Board'!$E$3:$E$180,"RB",'Draft Board'!$H$3:$H$180,$H6) -> 0 | K6: =COUNTIFS('Draft Board'!$A$3:$A$180,"★",'Draft Board'!$E$3:$E$180,"WR",'Draft Board'!$H$3:$H$180,$H6) -> 0 | L6: =COUNTIFS('Draft Board'!$A$3:$A$180,"★",'Draft Board'!$E$3:$E$180,"TE",'Draft Board'!$H$3:$H$180,$H6) -> 0 | M6: =SUM(I6:L6) -> 0 | N6: =IF(OR(J6>=2,K6>=2),"⚠ 2+ same position",IF(M6>=3,"Heavy week",""))
H7: 7 | I7: =COUNTIFS('Draft Board'!$A$3:$A$180,"★",'Draft Board'!$E$3:$E$180,"QB",'Draft Board'!$H$3:$H$180,$H7) -> 0 | J7: =COUNTIFS('Draft Board'!$A$3:$A$180,"★",'Draft Board'!$E$3:$E$180,"RB",'Draft Board'!$H$3:$H$180,$H7) -> 0 | K7: =COUNTIFS('Draft Board'!$A$3:$A$180,"★",'Draft Board'!$E$3:$E$180,"WR",'Draft Board'!$H$3:$H$180,$H7) -> 0 | L7: =COUNTIFS('Draft Board'!$A$3:$A$180,"★",'Draft Board'!$E$3:$E$180,"TE",'Draft Board'!$H$3:$H$180,$H7) -> 0 | M7: =SUM(I7:L7) -> 0 | N7: =IF(OR(J7>=2,K7>=2),"⚠ 2+ same position",IF(M7>=3,"Heavy week",""))
H8: 8 | I8: =COUNTIFS('Draft Board'!$A$3:$A$180,"★",'Draft Board'!$E$3:$E$180,"QB",'Draft Board'!$H$3:$H$180,$H8) -> 0 | J8: =COUNTIFS('Draft Board'!$A$3:$A$180,"★",'Draft Board'!$E$3:$E$180,"RB",'Draft Board'!$H$3:$H$180,$H8) -> 0 | K8: =COUNTIFS('Draft Board'!$A$3:$A$180,"★",'Draft Board'!$E$3:$E$180,"WR",'Draft Board'!$H$3:$H$180,$H8) -> 0 | L8: =COUNTIFS('Draft Board'!$A$3:$A$180,"★",'Draft Board'!$E$3:$E$180,"TE",'Draft Board'!$H$3:$H$180,$H8) -> 0 | M8: =SUM(I8:L8) -> 0 | N8: =IF(OR(J8>=2,K8>=2),"⚠ 2+ same position",IF(M8>=3,"Heavy week",""))
H9: 9 | I9: =COUNTIFS('Draft Board'!$A$3:$A$180,"★",'Draft Board'!$E$3:$E$180,"QB",'Draft Board'!$H$3:$H$180,$H9) -> 0 | J9: =COUNTIFS('Draft Board'!$A$3:$A$180,"★",'Draft Board'!$E$3:$E$180,"RB",'Draft Board'!$H$3:$H$180,$H9) -> 0 | K9: =COUNTIFS('Draft Board'!$A$3:$A$180,"★",'Draft Board'!$E$3:$E$180,"WR",'Draft Board'!$H$3:$H$180,$H9) -> 0 | L9: =COUNTIFS('Draft Board'!$A$3:$A$180,"★",'Draft Board'!$E$3:$E$180,"TE",'Draft Board'!$H$3:$H$180,$H9) -> 0 | M9: =SUM(I9:L9) -> 0 | N9: =IF(OR(J9>=2,K9>=2),"⚠ 2+ same position",IF(M9>=3,"Heavy week",""))
H10: 10 | I10: =COUNTIFS('Draft Board'!$A$3:$A$180,"★",'Draft Board'!$E$3:$E$180,"QB",'Draft Board'!$H$3:$H$180,$H10) -> 0 | J10: =COUNTIFS('Draft Board'!$A$3:$A$180,"★",'Draft Board'!$E$3:$E$180,"RB",'Draft Board'!$H$3:$H$180,$H10) -> 0 | K10: =COUNTIFS('Draft Board'!$A$3:$A$180,"★",'Draft Board'!$E$3:$E$180,"WR",'Draft Board'!$H$3:$H$180,$H10) -> 0 | L10: =COUNTIFS('Draft Board'!$A$3:$A$180,"★",'Draft Board'!$E$3:$E$180,"TE",'Draft Board'!$H$3:$H$180,$H10) -> 0 | M10: =SUM(I10:L10) -> 0 | N10: =IF(OR(J10>=2,K10>=2),"⚠ 2+ same position",IF(M10>=3,"Heavy week",""))
H11: 11 | I11: =COUNTIFS('Draft Board'!$A$3:$A$180,"★",'Draft Board'!$E$3:$E$180,"QB",'Draft Board'!$H$3:$H$180,$H11) -> 0 | J11: =COUNTIFS('Draft Board'!$A$3:$A$180,"★",'Draft Board'!$E$3:$E$180,"RB",'Draft Board'!$H$3:$H$180,$H11) -> 0 | K11: =COUNTIFS('Draft Board'!$A$3:$A$180,"★",'Draft Board'!$E$3:$E$180,"WR",'Draft Board'!$H$3:$H$180,$H11) -> 0 | L11: =COUNTIFS('Draft Board'!$A$3:$A$180,"★",'Draft Board'!$E$3:$E$180,"TE",'Draft Board'!$H$3:$H$180,$H11) -> 0 | M11: =SUM(I11:L11) -> 0 | N11: =IF(OR(J11>=2,K11>=2),"⚠ 2+ same position",IF(M11>=3,"Heavy week",""))
H12: 12 | I12: =COUNTIFS('Draft Board'!$A$3:$A$180,"★",'Draft Board'!$E$3:$E$180,"QB",'Draft Board'!$H$3:$H$180,$H12) -> 0 | J12: =COUNTIFS('Draft Board'!$A$3:$A$180,"★",'Draft Board'!$E$3:$E$180,"RB",'Draft Board'!$H$3:$H$180,$H12) -> 0 | K12: =COUNTIFS('Draft Board'!$A$3:$A$180,"★",'Draft Board'!$E$3:$E$180,"WR",'Draft Board'!$H$3:$H$180,$H12) -> 0 | L12: =COUNTIFS('Draft Board'!$A$3:$A$180,"★",'Draft Board'!$E$3:$E$180,"TE",'Draft Board'!$H$3:$H$180,$H12) -> 0 | M12: =SUM(I12:L12) -> 0 | N12: =IF(OR(J12>=2,K12>=2),"⚠ 2+ same position",IF(M12>=3,"Heavy week",""))
H13: 13 | I13: =COUNTIFS('Draft Board'!$A$3:$A$180,"★",'Draft Board'!$E$3:$E$180,"QB",'Draft Board'!$H$3:$H$180,$H13) -> 0 | J13: =COUNTIFS('Draft Board'!$A$3:$A$180,"★",'Draft Board'!$E$3:$E$180,"RB",'Draft Board'!$H$3:$H$180,$H13) -> 0 | K13: =COUNTIFS('Draft Board'!$A$3:$A$180,"★",'Draft Board'!$E$3:$E$180,"WR",'Draft Board'!$H$3:$H$180,$H13) -> 0 | L13: =COUNTIFS('Draft Board'!$A$3:$A$180,"★",'Draft Board'!$E$3:$E$180,"TE",'Draft Board'!$H$3:$H$180,$H13) -> 0 | M13: =SUM(I13:L13) -> 0 | N13: =IF(OR(J13>=2,K13>=2),"⚠ 2+ same position",IF(M13>=3,"Heavy week",""))
H14: 14 | I14: =COUNTIFS('Draft Board'!$A$3:$A$180,"★",'Draft Board'!$E$3:$E$180,"QB",'Draft Board'!$H$3:$H$180,$H14) -> 0 | J14: =COUNTIFS('Draft Board'!$A$3:$A$180,"★",'Draft Board'!$E$3:$E$180,"RB",'Draft Board'!$H$3:$H$180,$H14) -> 0 | K14: =COUNTIFS('Draft Board'!$A$3:$A$180,"★",'Draft Board'!$E$3:$E$180,"WR",'Draft Board'!$H$3:$H$180,$H14) -> 0 | L14: =COUNTIFS('Draft Board'!$A$3:$A$180,"★",'Draft Board'!$E$3:$E$180,"TE",'Draft Board'!$H$3:$H$180,$H14) -> 0 | M14: =SUM(I14:L14) -> 0 | N14: =IF(OR(J14>=2,K14>=2),"⚠ 2+ same position",IF(M14>=3,"Heavy week",""))

Sheet Draft Board
C1: ◄ Fuzzy search: type any part of a player name; non-matching rows hide. Clear the box to reset. (Google Sheets: add the one-time Apps Script — see chat.)
A2: Drafted | B2: Ovr | C2: Rec Rd | D2: Player | E2: Pos | F2: Pos Rk | G2: Team | H2: Bye | I2: ADP | J2: Exp Rk | K2: Value | L2: Verdict | M2: Flag | N2: Notes | O2: PPR Lean
A3: ☐ | B3: 1 | C3: R1 | D3: Jahmyr Gibbs | E3: RB | F3: 1 | G3: Detroit Lions | H3: 6 | I3: 1.5 | J3: 1 | K3: 0 | L3: Fair | N3: [Sep 3] Workload bump: Isiah Pacheco (IR) is out to start the season, funneling more Detroit backfield work to Gibbs. 🎯 R1 TARGET · Fairly valued vs the market. Target ~R1; don't reach much earlier. | O3: ● Role
A4: ☐ | B4: 2 | C4: R1 | D4: Bijan Robinson | E4: RB | F4: 2 | G4: Atlanta Falcons | H4: 11 | I4: 2.3 | J4: 2 | K4: 0 | L4: Fair | N4: 🎯 R1 TARGET · Fairly valued vs the market. Target ~R1; don't reach much earlier. | O4: ● Role
A5: ☐ | B5: 3 | C5: R1 | D5: Ja'Marr Chase | E5: WR | F5: 1 | G5: Cincinnati Bengals | H5: 6 | I5: 3.9 | J5: 3 | K5: +1 | L5: Fair | N5: 🎯 R1 TARGET · Fairly valued vs the market. Target ~R1; don't reach much earlier. | O5: ▲ Up
A6: ☐ | B6: 4 | C6: R1 | D6: Jaxon Smith-Njigba | E6: WR | F6: 2 | G6: Seattle Seahawks | H6: 11 | I6: 5.4 | J6: 5 | K6: 0 | L6: Fair | N6: Fairly valued vs the market. Target ~R1; don't reach much earlier. | O6: ▲ Up
A7: ☐ | B7: 5 | C7: R1 | D7: Jonathan Taylor | E7: RB | F7: 3 | G7: Indianapolis Colts | H7: 13 | I7: 6 | J7: 7 | K7: -1 | L7: Fair | N7: Fairly valued vs the market. Target ~R1; don't reach much earlier. | O7: ● Role
A8: ☐ | B8: 6 | C8: R1 | D8: Christian McCaffrey | E8: RB | F8: 4 | G8: San Francisco 49ers | H8: 8 | I8: 6.8 | J8: 6 | K8: +1 | L8: Fair | M8: Back to full practice — Wk1 expected (age/workload watch) | N8: [Sep 3] Returned to full practice & team drills; expected to play Wk1 vs LAR. The camp 'tightness' was calf/load-management; durability caveat remains (age 30, 413 touches in '25). INJURY: missed camp with 'tightness'; age 30, injury-prone (413 touches in 2025). Elite but risky at a Round-1 price. | O8: ● Role
A9: ☐ | B9: 7 | C9: R1 | D9: Amon-Ra St. Brown | E9: WR | F9: 3 | G9: Detroit Lions | H9: 6 | I9: 7.9 | J9: 8 | K9: 0 | L9: Fair | N9: Fairly valued vs the market. Target ~R1; don't reach much earlier. | O9: ▲ Up
A10: ☐ | B10: 8 | C10: R1 | D10: James Cook | E10: RB | F10: 5 | G10: Buffalo Bills | H10: 7 | I10: 9.2 | J10: 10 | K10: -1 | L10: Fair | N10: Fairly valued vs the market. Target ~R1; don't reach much earlier. | O10: ● Role
A11: ☐ | B11: 9 | C11: R1 | D11: De'Von Achane | E11: RB | F11: 6 | G11: Miami Dolphins | H11: 6 | I11: 11.5 | J11: 13 | K11: -2 | L11: Fair | N11: Fairly valued vs the market. Target ~R1; don't reach much earlier. | O11: ● Role
A12: ☐ | B12: 10 | C12: R1 | D12: CeeDee Lamb | E12: WR | F12: 4 | G12: Dallas Cowboys | H12: 14 | I12: 12.5 | J12: 9 | K12: +4 | L12: Fair | N12: Fairly valued vs the market. Target ~R1; don't reach much earlier. | O12: ▲ Up
A13: ☐ | B13: 11 | C13: R2 | D13: Puka Nacua | E13: WR | F13: 5 | G13: Los Angeles Rams | H13: 11 | I13: 3.1 | J13: 4 | K13: -1 | L13: Fair | M13: Not on exempt list (Sep 1) — likely Wk1; small lingering risk | N13: [Sep 3] NOT placed on the commissioner's exempt list as of Sep 1 and no suspension announced; civil case pushed past Sep 7. Suspension risk is materially reduced — likely plays Wk1. SUSPENSION RISK: under NFL review; missing the Sept 10 Melbourne opener is 'on the table,' no ruling as of Aug 27. Elite when active — price in games-missed risk. | O13: ▲ Up
A14: ☐ | B14: 12 | C14: R2 | D14: Derrick Henry | E14: RB | F14: 7 | G14: Baltimore Ravens | H14: 13 | I14: 9.9 | J14: 17 | K14: -7 | L14: OVERVALUED | N14: Fairly valued vs the market. Target ~R2; don't reach much earlier. | O14: ● Role
A15: ☐ | B15: 13 | C15: R2 | D15: Drake London | E15: WR | F15: 6 | G15: Atlanta Falcons | H15: 11 | I15: 12.4 | J15: 15 | K15: -3 | L15: Fair | N15: Fairly valued vs the market. Target ~R2; don't reach much earlier. | O15: ▲ Up
A16: ☐ | B16: 14 | C16: R2 | D16: Justin Jefferson | E16: WR | F16: 7 | G16: Minnesota Vikings | H16: 6 | I16: 14.1 | J16: 12 | K16: +2 | L16: Fair | N16: Fairly valued vs the market. Target ~R2; don't reach much earlier. | O16: ▲ Up
A17: ☐ | B17: 15 | C17: R2 | D17: Ashton Jeanty | E17: RB | F17: 8 | G17: Las Vegas Raiders | H17: 13 | I17: 15.1 | J17: 11 | K17: +4 | L17: Fair | M17: Ankle — made 53-man, no return date; monitor | N17: [Sep 3] Ankle injury: made the 53-man roster but the Raiders set no return date — a real Wk1 risk at a Round-2 price. Mike Washington Jr. is the contingency. Fairly valued vs the market. Target ~R2; don't reach much earlier. | O17: ● Role
A18: ☐ | B18: 16 | C18: R2 | D18: Chase Brown | E18: RB | F18: 9 | G18: Cincinnati Bengals | H18: 6 | I18: 15.1 | J18: 16 | K18: 0 | L18: Fair | N18: Fairly valued vs the market. Target ~R2; don't reach much earlier. | O18: ● Role
A19: ☐ | B19: 17 | C19: R2 | D19: Rashee Rice | E19: WR | F19: 8 | G19: Kansas City Chiefs | H19: 5 | I19: 15.9 | J19: 26 | K19: -9 | L19: OVERVALUED | M19: CLEARED — NFL closed investigation (Apr 2026), no discipline | N19: [Sep 3] Fully clear: the NFL closed its personal-conduct investigation in April 2026 with no discipline. Available Wk1. SUSPENSION (cleared): off-field matter reported settled, not expected to be suspended. Treat as clear; monitor. | O19: ▲ Up
A20: ☐ | B20: 18 | C20: R2 | D20: Saquon Barkley | E20: RB | F20: 10 | G20: Philadelphia Eagles | H20: 10 | I20: 17.3 | J20: 14 | K20: +4 | L20: Fair | N20: Fairly valued vs the market. Target ~R2; don't reach much earlier. | O20: ● Role
A21: ☐ | B21: 19 | C21: R2 | D21: A.J. Brown | E21: WR | F21: 9 | G21: New England Patriots | H21: 11 | I21: 19.6 | J21: 18 | K21: +1 | L21: Fair | N21: Fairly valued vs the market. Target ~R2; don't reach much earlier. | O21: ▲ Up
A22: ☐ | B22: 20 | C22: R2 | D22: George Pickens | E22: WR | F22: 10 | G22: Dallas Cowboys | H22: 14 | I22: 19.6 | J22: 24 | K22: -4 | L22: Fair | N22: Fairly valued vs the market. Target ~R2; don't reach much earlier. | O22: ▲ Up
A23: ☐ | B23: 21 | C23: R2 | D23: Nico Collins | E23: WR | F23: 11 | G23: Houston Texans | H23: 8 | I23: 21.5 | J23: 23 | K23: -2 | L23: Fair | N23: Fairly valued vs the market. Target ~R2; don't reach much earlier. | O23: ▲ Up
A24: ☐ | B24: 22 | C24: R2 | D24: Kenneth Walker III | E24: RB | F24: 11 | G24: Kansas City Chiefs | H24: 5 | I24: 21.6 | J24: 19 | K24: +3 | L24: Fair | N24: Fairly valued vs the market. Target ~R2; don't reach much earlier. | O24: ● Role
A25: ☐ | B25: 23 | C25: R2 | D25: Omarion Hampton | E25: RB | F25: 12 | G25: Los Angeles Chargers | H25: 7 | I25: 23.6 | J25: 21 | K25: +2 | L25: Fair | N25: Fairly valued vs the market. Target ~R2; don't reach much earlier. | O25: ● Role
A26: ☐ | B26: 24 | C26: R3 | D26: Chris Olave | E26: WR | F26: 12 | G26: New Orleans Saints | H26: 8 | I26: 23.9 | J26: 28 | K26: -4 | L26: Fair | N26: 🎯 R2 TARGET · Riser — benefits if Tyson misses; worth late R2 / early R3. | O26: ▲ Up
A27: ☐ | B27: 25 | C27: R3 | D27: Zay Flowers | E27: WR | F27: 13 | G27: Baltimore Ravens | H27: 13 | I27: 25.3 | J27: 39 | K27: -13 | L27: OVERVALUED | N27: 🎯 R2 TARGET · Market drafts him ~13 spots ahead of the Aug-9 expert board (ADP ~R3) — fade, or he's risen since. | O27: ▲ Up
A28: ☐ | B28: 26 | C28: R3 | D28: Kyren Williams | E28: RB | F28: 13 | G28: Los Angeles Rams | H28: 11 | I28: 27 | J28: 30 | K28: -3 | L28: Fair | N28: 🎯 R2 TARGET · Fairly valued vs the market. Target ~R3; don't reach much earlier. | O28: ● Role
A29: ☐ | B29: 27 | C29: R3 | D29: Malik Nabers | E29: WR | F29: 14 | G29: New York Giants | H29: 8 | I29: 28.2 | J29: 29 | K29: -1 | L29: Fair | M29: Post-ACL — ramping to Wk1, top-10 upside | N29: [Sep 3] ACL recovery on track; ramping up in practice, experts eyeing a top-10 WR finish and ADP trending up. Confirm full team-drill participation before Wk1. 🎯 R3 TARGET · INJURY: post-ACL, back at practice, on track for Week 1 (worst case miss 1-2). Trending up — possible value. | O29: ▲ Up
A30: ☐ | B30: 28 | C30: R3 | D30: Garrett Wilson | E30: WR | F30: 15 | G30: New York Jets | H30: 13 | I30: 31.4 | J30: 40 | K30: -10 | L30: OVERVALUED | N30: 🎯 R3 TARGET · Fairly valued vs the market. Target ~R3; don't reach much earlier. | O30: ▲ Up
A31: ☐ | B31: 29 | C31: R3 | D31: DeVonta Smith | E31: WR | F31: 16 | G31: Philadelphia Eagles | H31: 10 | I31: 32 | J31: 36 | K31: -5 | L31: Fair | N31: 🎯 R3 TARGET · Fairly valued vs the market. Target ~R3; don't reach much earlier. | O31: ▲ Up
A32: ☐ | B32: 30 | C32: R3 | D32: Tetairoa McMillan | E32: WR | F32: 17 | G32: Carolina Panthers | H32: 5 | I32: 32.2 | J32: 35 | K32: -3 | L32: Fair | N32: Fairly valued vs the market. Target ~R3; don't reach much earlier. | O32: ▲ Up
A33: ☐ | B33: 31 | C33: R3 | D33: Josh Allen | E33: QB | F33: 1 | G33: Buffalo Bills | H33: 7 | I33: 32.9 | J33: 25 | K33: +8 | L33: UNDERVALUED | N33: Fairly valued vs the market. Target ~R3; don't reach much earlier. | O33: =
A34: ☐ | B34: 32 | C34: R3 | D34: Javonte Williams | E34: RB | F34: 14 | G34: Dallas Cowboys | H34: 14 | I34: 33.6 | J34: 34 | K34: 0 | L34: Fair | N34: Fairly valued vs the market. Target ~R3; don't reach much earlier. | O34: ● Role
A35: ☐ | B35: 33 | C35: R3 | D35: Tee Higgins | E35: WR | F35: 18 | G35: Cincinnati Bengals | H35: 6 | I35: 36.5 | J35: 33 | K35: +5 | L35: Fair | N35: Fairly valued vs the market. Target ~R3; don't reach much earlier. | O35: ▲ Up
A36: ☐ | B36: 34 | C36: R3 | D36: Trey McBride | E36: TE | F36: 1 | G36: Arizona Cardinals | H36: 14 | I36: 38.2 | J36: 22 | K36: +17 | L36: UNDERVALUED | N36: Experts' TE2; market ~R4. Second shot at the premium-TE tier. | O36: ▲ Up
A37: ☐ | B37: 35 | C37: R3 | D37: Brock Bowers | E37: TE | F37: 2 | G37: Las Vegas Raiders | H37: 13 | I37: 43 | J37: 20 | K37: +24 | L37: UNDERVALUED | N37: Experts' TE1, ranked well above where the market drafts him (~R4). Elite TE edge if you want it. | O37: ▲ Up
A38: ☐ | B38: 36 | C38: R4 | D38: Josh Jacobs | E38: RB | F38: 15 | G38: Green Bay Packers | H38: 11 | I38: 24.9 | J38: 31 | K38: -6 | L38: OVERVALUED | M38: ON COMMISSIONER'S EXEMPT LIST (Aug 30) — out indefinitely | N38: [Sep 3] Placed on the NFL Commissioner's Exempt List Aug 30 (formal misdemeanor charges) — cannot practice or play; out indefinitely to start the season (games-missed range 0-17, ~6 most likely). Draft only as a late stash. GB backfield now MarShawn Lloyd + newly traded-for Kaleb Johnson. INJURY + SUSPENSION: camp groin, plus a possible suspension (May arrest) still under review. Double risk; MarShawn Lloyd is the handcuff. | O38: ● Role
A39: ☐ | B39: 37 | C39: R4 | D39: Jeremiyah Love | E39: RB | F39: 16 | G39: Arizona Cardinals | H39: 14 | I39: 30 | J39: 27 | K39: +2 | L39: Fair | M39: High ankle sprain — ~50/50 for Wk1 | N39: INJURY: high ankle sprain, ~50/50 for Week 1 with a 1-2 game ramp. Don't draft above ~Round 4. | O39: ● Role
A40: ☐ | B40: 38 | C40: R4 | D40: Cam Skattebo | E40: RB | F40: 17 | G40: New York Giants | H40: 8 | I40: 34.3 | J40: 43 | K40: -8 | L40: OVERVALUED | N40: Fairly valued vs the market. Target ~R4; don't reach much earlier. | O40: ● Role
A41: ☐ | B41: 39 | C41: R4 | D41: Breece Hall | E41: RB | F41: 18 | G41: New York Jets | H41: 13 | I41: 34.9 | J41: 32 | K41: +4 | L41: Fair | M41: Groin — ~2-3 weeks | N41: INJURY: groin, out ~2-3 weeks. Monitor Week 1; Braelon Allen is the handcuff. | O41: ● Role
A42: ☐ | B42: 40 | C42: R4 | D42: Emeka Egbuka | E42: WR | F42: 19 | G42: Tampa Bay Buccaneers | H42: 10 | I42: 34.9 | J42: 42 | K42: -5 | L42: Fair | M42: Toe — Wk1 status uncertain | N42: 💤 SLEEPER — ascending target share in TB; efficient rookie profile (monitor toe). INJURY: toe, Week 1 status uncertain. Monitor before starting. | O42: ▲ Up
A43: ☐ | B43: 41 | C43: R4 | D43: Davante Adams | E43: WR | F43: 20 | G43: Los Angeles Rams | H43: 11 | I43: 38.4 | J43: 49 | K43: -9 | L43: OVERVALUED | N43: Fairly valued vs the market. Target ~R4; don't reach much earlier. | O43: ▲ Up
A44: ☐ | B44: 42 | C44: R4 | D44: Travis Etienne Jr. | E44: RB | F44: 19 | G44: New Orleans Saints | H44: 8 | I44: 40.1 | J44: 38 | K44: +3 | L44: Fair | N44: Fairly valued vs the market. Target ~R4; don't reach much earlier. | O44: ● Role
A45: ☐ | B45: 43 | C45: R4 | D45: Ladd McConkey | E45: WR | F45: 21 | G45: Los Angeles Chargers | H45: 7 | I45: 41.2 | J45: 45 | K45: -2 | L45: Fair | N45: Fairly valued vs the market. Target ~R4; don't reach much earlier. | O45: ▲ Up
A46: ☐ | B46: 44 | C46: R4 | D46: Bucky Irving | E46: RB | F46: 20 | G46: Tampa Bay Buccaneers | H46: 10 | I46: 45.5 | J46: 44 | K46: +3 | L46: Fair | N46: Fairly valued vs the market. Target ~R4; don't reach much earlier. | O46: ● Role
A47: ☐ | B47: 45 | C47: R4 | D47: Jaylen Waddle | E47: WR | F47: 22 | G47: Denver Broncos | H47: 10 | I47: 47.7 | J47: 46 | K47: +3 | L47: Fair | N47: Fairly valued vs the market. Target ~R4; don't reach much earlier. | O47: ▲ Up
A48: ☐ | B48: 46 | C48: R4 | D48: Lamar Jackson | E48: QB | F48: 2 | G48: Baltimore Ravens | H48: 13 | I48: 56.7 | J48: 37 | K48: +22 | L48: UNDERVALUED | N48: Experts' QB2; market waits ~R5. Wait-on-QB reward. | O48: =
A49: ☐ | B49: 47 | C49: R5 | D49: Jameson Williams | E49: WR | F49: 23 | G49: Detroit Lions | H49: 6 | I49: 40.4 | J49: 56 | K49: -14 | L49: OVERVALUED | N49: Market drafts him ~14 spots ahead of the Aug-9 expert board (ADP ~R4) — fade, or he's risen since. | O49: ▲ Up
A50: ☐ | B50: 48 | C50: R5 | D50: D'Andre Swift | E50: RB | F50: 21 | G50: Chicago Bears | H50: 10 | I50: 43.3 | J50: 52 | K50: -7 | L50: OVERVALUED | M50: Bigger role — Monangai (knee) out weeks | N50: [Sep 3] Value bump: Kyle Monangai's hyperextended knee opens a larger early-down role for Swift to start the year. 🎯 R4 TARGET · Fairly valued vs the market. Target ~R5; don't reach much earlier. | O50: ● Role
A51: ☐ | B51: 49 | C51: R5 | D51: Terry McLaurin | E51: WR | F51: 24 | G51: Washington Commanders | H51: 7 | I51: 45 | J51: 54 | K51: -8 | L51: OVERVALUED | N51: 🎯 R4 TARGET · Fairly valued vs the market. Target ~R5; don't reach much earlier. | O51: ▲ Up
A52: ☐ | B52: 50 | C52: R5 | D52: Rome Odunze | E52: WR | F52: 25 | G52: Chicago Bears | H52: 10 | I52: 47.3 | J52: 64 | K52: -16 | L52: OVERVALUED | N52: 🎯 R4 TARGET · 💤 SLEEPER — clear Bears WR1 with Burden hurt; target-share breakout. Bump up — clearly the Bears' WR1 with Burden hurt. | O52: ▲ Up
A53: ☐ | B53: 51 | C53: R5 | D53: D.J. Moore | E53: WR | F53: 26 | G53: Buffalo Bills | H53: 7 | I53: 50.6 | J53: 60 | K53: -10 | L53: OVERVALUED | M53: Minor ankle — precaution | N53: 🎯 R5 TARGET · INJURY: minor ankle (precaution). Minimal impact. | O53: ▲ Up
A54: ☐ | B54: 52 | C54: R5 | D54: Quinshon Judkins | E54: RB | F54: 22 | G54: Cleveland Browns | H54: 11 | I54: 51.4 | J54: 47 | K54: +4 | L54: Fair | N54: 🎯 R5 TARGET · Fairly valued vs the market. Target ~R5; don't reach much earlier. | O54: ● Role
A55: ☐ | B55: 53 | C55: R5 | D55: Drake Maye | E55: QB | F55: 3 | G55: New England Patriots | H55: 11 | I55: 51.9 | J55: 50 | K55: +2 | L55: Fair | N55: 🎯 R5 TARGET · Fairly valued vs the market. Target ~R5; don't reach much earlier. | O55: =
A56: ☐ | B56: 54 | C56: R5 | D56: Bhayshul Tuten | E56: RB | F56: 23 | G56: Jacksonville Jaguars | H56: 7 | I56: 53.4 | J56: 61 | K56: -8 | L56: OVERVALUED | N56: 💤 SLEEPER — big-play rookie with a clear path to JAX RB2/flex value; league-winner upside. Fairly valued vs the market. Target ~R5; don't reach much earlier. | O56: ● Role
A57: ☐ | B57: 55 | C57: R5 | D57: Mike Evans | E57: WR | F57: 27 | G57: San Francisco 49ers | H57: 8 | I57: 53.8 | J57: 58 | K57: -4 | L57: Fair | M57: Minor groin — plans to play Wk1 | N57: INJURY: groin ('minor'); plans to play Week 1. Solid WR2 if healthy. | O57: ▲ Up
A58: ☐ | B58: 56 | C58: R5 | D58: David Montgomery | E58: RB | F58: 24 | G58: Houston Texans | H58: 8 | I58: 55 | J58: 51 | K58: +4 | L58: Fair | N58: Fairly valued vs the market. Target ~R5; don't reach much earlier. | O58: ● Role
A59: ☐ | B59: 57 | C59: R5 | D59: Christian Watson | E59: WR | F59: 28 | G59: Green Bay Packers | H59: 11 | I59: 56.3 | J59: 59 | K59: -3 | L59: Fair | N59: Fairly valued vs the market. Target ~R5; don't reach much earlier. | O59: ▲ Up
A60: ☐ | B60: 58 | C60: R5 | D60: Joe Burrow | E60: QB | F60: 4 | G60: Cincinnati Bengals | H60: 6 | I60: 56.4 | J60: 55 | K60: +2 | L60: Fair | N60: Fairly valued vs the market. Target ~R5; don't reach much earlier. | O60: =
A61: ☐ | B61: 59 | C61: R5 | D61: TreVeyon Henderson | E61: RB | F61: 25 | G61: New England Patriots | H61: 11 | I61: 60.2 | J61: 53 | K61: +8 | L61: UNDERVALUED | N61: 💤 SLEEPER — elite explosiveness + receiving; breakout if he takes the NE backfield from Stevenson. Fairly valued vs the market. Target ~R5; don't reach much earlier. | O61: ● Role
A62: ☐ | B62: 60 | C62: R5 | D62: Colston Loveland | E62: TE | F62: 3 | G62: Chicago Bears | H62: 10 | I62: 61.3 | J62: 41 | K62: +21 | L62: UNDERVALUED | N62: Experts high on this rookie TE (TE3); market ~R6. Rookie variance. | O62: ▲ Up
A63: ☐ | B63: 61 | C63: R6 | D63: Courtland Sutton | E63: WR | F63: 29 | G63: Denver Broncos | H63: 10 | I63: 59.7 | J63: 78 | K63: -18 | L63: OVERVALUED | N63: Market drafts him ~18 spots ahead of the Aug-9 expert board (ADP ~R5) — fade, or he's risen since. | O63: ▲ Up
A64: ☐ | B64: 62 | C64: R6 | D64: Luther Burden III | E64: WR | F64: 30 | G64: Chicago Bears | H64: 10 | I64: 61.7 | J64: 48 | K64: +15 | L64: UNDERVALUED | M64: Groin — ~1 month, hopeful Wk1 | N64: 💤 SLEEPER — Ben Johnson offense + ~150 vacated targets; elite YAC — big breakout once healthy. INJURY: groin (Aug 8), out ~a month, hopeful for Week 1. Now WR2 behind Rome Odunze — risky at ADP. | O64: ▲ Up
A65: ☐ | B65: 63 | C65: R6 | D65: Jaylen Warren | E65: RB | F65: 26 | G65: Pittsburgh Steelers | H65: 9 | I65: 63.1 | J65: 65 | K65: -1 | L65: Fair | N65: 💤 SLEEPER — PIT committee with real standalone value; smash play if Dowdle misses time. Fairly valued vs the market. Target ~R6; don't reach much earlier. | O65: ● Role
A66: ☐ | B66: 64 | C66: R6 | D66: DK Metcalf | E66: WR | F66: 31 | G66: Pittsburgh Steelers | H66: 9 | I66: 63.3 | J66: 75 | K66: -10 | L66: OVERVALUED | N66: Fairly valued vs the market. Target ~R6; don't reach much earlier. | O66: ▲ Up
A67: ☐ | B67: 65 | C67: R6 | D67: Marvin Harrison Jr. | E67: WR | F67: 32 | G67: Arizona Cardinals | H67: 14 | I67: 65 | J67: 70 | K67: -3 | L67: Fair | N67: Fairly valued vs the market. Target ~R6; don't reach much earlier. | O67: ▲ Up
A68: ☐ | B68: 66 | C68: R6 | D68: Tony Pollard | E68: RB | F68: 27 | G68: Tennessee Titans | H68: 9 | I68: 66.1 | J68: 68 | K68: +1 | L68: Fair | N68: Fairly valued vs the market. Target ~R6; don't reach much earlier. | O68: ● Role
A69: ☐ | B69: 67 | C69: R6 | D69: Rhamondre Stevenson | E69: RB | F69: 28 | G69: New England Patriots | H69: 11 | I69: 68.5 | J69: 71 | K69: -1 | L69: Fair | N69: Fairly valued vs the market. Target ~R6; don't reach much earlier. | O69: ● Role
A70: ☐ | B70: 68 | C70: R6 | D70: Brian Thomas Jr. | E70: WR | F70: 33 | G70: Jacksonville Jaguars | H70: 7 | I70: 69.5 | J70: 73 | K70: -2 | L70: Fair | N70: Fairly valued vs the market. Target ~R6; don't reach much earlier. | O70: ▲ Up
A71: ☐ | B71: 69 | C71: R6 | D71: Tyler Warren | E71: TE | F71: 4 | G71: Indianapolis Colts | H71: 13 | I71: 70.4 | J71: 57 | K71: +15 | L71: UNDERVALUED | M71: Adductor — minor; Wk1 not in jeopardy | N71: [Sep 3] Adductor strain confirmed minor; Wk1 is not in serious jeopardy. 💤 SLEEPER — elite projected TE volume in IND; breakout (monitor adductor). INJURY: adductor strain (~1 week); Week 1 not in serious jeopardy. Minimal draft impact. | O71: ▲ Up
A72: ☐ | B72: 70 | C72: R6 | D72: Jayden Daniels | E72: QB | F72: 5 | G72: Washington Commanders | H72: 7 | I72: 71 | J72: 63 | K72: +10 | L72: UNDERVALUED | N72: Experts rank him ~10 spots above the market (ADP ~R6). QB value if you trust the board. | O72: =
A73: ☐ | B73: 71 | C73: R6 | D73: Carnell Tate | E73: WR | F73: 34 | G73: Tennessee Titans | H73: 9 | I73: 73.9 | J73: 66 | K73: +8 | L73: UNDERVALUED | N73: 💤 SLEEPER — pro-ready rookie, TEN's new go-to target. Fairly valued vs the market. Target ~R6; don't reach much earlier. | O73: ▲ Up
A74: ☐ | B74: 72 | C74: R6 | D74: Jadarian Price | E74: RB | F74: 29 | G74: Seattle Seahawks | H74: 11 | I74: 75.3 | J74: 67 | K74: +9 | L74: UNDERVALUED | M74: SEA lead back — Charbonnet (IR) out ~4 wks | N74: [Sep 3] With Zach Charbonnet on IR (~first 4 games), rookie Price is positioned to lead the Seattle backfield — startable sleeper; George Holani handles passing downs. 🎯 R6 TARGET · 💤 SLEEPER — first-round rookie workhorse in a strong SEA run game; immediate volume. Fairly valued vs the market. Target ~R6; don't reach much earlier. | O74: ● Role
A75: ☐ | B75: 73 | C75: R6 | D75: Jalen Hurts | E75: QB | F75: 6 | G75: Philadelphia Eagles | H75: 10 | I75: 80.9 | J75: 62 | K75: +18 | L75: UNDERVALUED | N75: 🎯 R6 TARGET · Experts' QB5; market ~R7. Rushing-floor QB at a discount. | O75: =
A76: ☐ | B76: 74 | C76: R7 | D76: Alec Pierce | E76: WR | F76: 35 | G76: Indianapolis Colts | H76: 13 | I76: 56.4 | J76: 80 | K76: -22 | L76: OVERVALUED | M76: PUP ankle — back to practice soon | N76: 🎯 R6 TARGET · INJURY: on PUP (ankle surgery) but expected back at practice this week; targeting Week 1. Boom/bust WR2 — confirm active. | O76: ▲ Up
A77: ☐ | B77: 75 | C77: R7 | D77: Parker Washington | E77: WR | F77: 36 | G77: Jacksonville Jaguars | H77: 7 | I77: 64.7 | J77: 87 | K77: -21 | L77: OVERVALUED | N77: 🎯 R7 TARGET · Riser — market ~R6 vs stale expert R8. | O77: ▲ Up
A78: ☐ | B78: 76 | C78: R7 | D78: Dak Prescott | E78: QB | F78: 7 | G78: Dallas Cowboys | H78: 14 | I78: 65.5 | J78: 79 | K78: -11 | L78: OVERVALUED | N78: 🎯 R7 TARGET · Fairly valued vs the market. Target ~R7; don't reach much earlier. | O78: =
A79: ☐ | B79: 77 | C79: R7 | D79: Rico Dowdle | E79: RB | F79: 30 | G79: Pittsburgh Steelers | H79: 9 | I79: 74.6 | J79: 72 | K79: +3 | L79: Fair | N79: 🎯 R7 TARGET · 💤 SLEEPER — splitting first-team reps in PIT; high-value touches at ~R7 cost. Fairly valued vs the market. Target ~R7; don't reach much earlier. | O79: ● Role
A80: ☐ | B80: 78 | C80: R7 | D80: Chuba Hubbard | E80: RB | F80: 31 | G80: Carolina Panthers | H80: 5 | I80: 77.6 | J80: 76 | K80: +2 | L80: Fair | M80: Hamstring — committee w/ Brooks | N80: INJURY: hamstring, week-to-week; committee with Jonathon Brooks to start. Reduced ceiling. | O80: ● Role
A81: ☐ | B81: 79 | C81: R7 | D81: Matthew Stafford | E81: QB | F81: 8 | G81: LAR | H81: 11 | I81: 78.3 | J81: — | K81: — | L81: Depth | N81: QB in a strong passing offense; ~R7 streamer. | O81: =
A82: ☐ | B82: 80 | C82: R7 | D82: Seattle DST | E82: DST | F82: 1 | G82: SEA | H82: 11 | I82: 81.8 | J82: — | K82: — | L82: — | N82: 🎯 TARGET · Top defense — draft a top-5 unit around R7-8 (don't wait to the last rounds). | O82: =
A83: ☐ | B83: 81 | C83: R7 | D83: J.K. Dobbins | E83: RB | F83: 32 | G83: Denver Broncos | H83: 10 | I83: 83.3 | J83: 85 | K83: -3 | L83: Fair | M83: Soft-tissue — may start slow | N83: INJURY: soft-tissue (hamstring); extensive injury history. Jonah Coleman could compete — slow-start/committee risk. | O83: ● Role
A84: ☐ | B84: 82 | C84: R7 | D84: Harold Fannin Jr. | E84: TE | F84: 5 | G84: Cleveland Browns | H84: 11 | I84: 83.8 | J84: 69 | K84: +14 | L84: UNDERVALUED | N84: Deep-sleeper rookie TE; experts TE5, market ~R7. | O84: ▲ Up
A85: ☐ | B85: 83 | C85: R7 | D85: Kyle Pitts | E85: TE | F85: 6 | G85: Atlanta Falcons | H85: 11 | I85: 85.2 | J85: 77 | K85: +7 | L85: UNDERVALUED | N85: Fairly valued vs the market. Target ~R7; don't reach much earlier. | O85: ▲ Up
A86: ☐ | B86: 84 | C86: R7 | D86: Tucker Kraft | E86: TE | F86: 7 | G86: Green Bay Packers | H86: 11 | I86: 100.5 | J86: 74 | K86: +17 | L86: UNDERVALUED | N86: Value TE (experts' TE5-6); market ~R9. No injury reported. | O86: ▲ Up
A87: ☐ | B87: 85 | C87: R8 | D87: Michael Wilson | E87: WR | F87: 37 | G87: Arizona Cardinals | H87: 14 | I87: 76.1 | J87: 97 | K87: -20 | L87: OVERVALUED | N87: Riser — market ~R7 vs stale expert R9. | O87: ▲ Up
A88: ☐ | B88: 86 | C88: R8 | D88: Chris Godwin | E88: WR | F88: 38 | G88: Tampa Bay Buccaneers | H88: 10 | I88: 77.6 | J88: 93 | K88: -14 | L88: OVERVALUED | N88: Market drafts him ~14 spots ahead of the Aug-9 expert board (ADP ~R7) — fade, or he's risen since. | O88: ▲ Up
A89: ☐ | B89: 87 | C89: R8 | D89: Michael Pittman Jr. | E89: WR | F89: 39 | G89: Pittsburgh Steelers | H89: 9 | I89: 81 | J89: 96 | K89: -15 | L89: OVERVALUED | N89: Market drafts him ~15 spots ahead of the Aug-9 expert board (ADP ~R7) — fade, or he's risen since. | O89: ▲ Up
A90: ☐ | B90: 88 | C90: R8 | D90: Jakobi Meyers | E90: WR | F90: 40 | G90: Jacksonville Jaguars | H90: 7 | I90: 85.9 | J90: 91 | K90: -6 | L90: OVERVALUED | N90: Fairly valued vs the market. Target ~R8; don't reach much earlier. | O90: ▲ Up
A91: ☐ | B91: 89 | C91: R8 | D91: Quentin Johnston | E91: WR | F91: 41 | G91: Los Angeles Chargers | H91: 7 | I91: 86.2 | J91: 94 | K91: -8 | L91: OVERVALUED | N91: Fairly valued vs the market. Target ~R8; don't reach much earlier. | O91: ▲ Up
A92: ☐ | B92: 90 | C92: R8 | D92: Josh Downs | E92: WR | F92: 42 | G92: IND | H92: 13 | I92: 87.7 | J92: — | K92: — | L92: Depth | M92: Calf — day-to-day | N92: 💤 SLEEPER — high-volume IND slot; PPR value, more if Pierce misses time. INJURY: calf, day-to-day. Slot value, especially if Pierce misses time. | O92: ▲ Up
A93: ☐ | B93: 91 | C93: R8 | D93: Jordan Addison | E93: WR | F93: 43 | G93: MIN | H93: 6 | I93: 88.1 | J93: — | K93: — | L93: Depth | N93: MIN WR2; ADP ~R8. | O93: ▲ Up
A94: ☐ | B94: 92 | C94: R8 | D94: Brock Purdy | E94: QB | F94: 9 | G94: SF | H94: 8 | I94: 88.4 | J94: — | K94: — | L94: Depth | N94: Streaming QB. | O94: =
A95: ☐ | B95: 93 | C95: R8 | D95: Caleb Williams | E95: QB | F95: 10 | G95: Chicago Bears | H95: 10 | I95: 91 | J95: 82 | K95: +5 | L95: Fair | N95: Fairly valued vs the market. Target ~R8; don't reach much earlier. | O95: =
A96: ☐ | B96: 94 | C96: R8 | D96: Jayden Reed | E96: WR | F96: 44 | G96: GB | H96: 11 | I96: 91.2 | J96: — | K96: — | L96: Depth | N96: GB WR; volatile week to week. | O96: ▲ Up
A97: ☐ | B97: 95 | C97: R8 | D97: Denver DST | E97: DST | F97: 2 | G97: DEN | H97: 10 | I97: 91.2 | J97: — | K97: — | L97: — | N97: 🎯 TARGET · Top defense — draft a top-5 unit around R7-8 (don't wait to the last rounds). | O97: =
A98: ☐ | B98: 96 | C98: R8 | D98: Wan'Dale Robinson | E98: WR | F98: 45 | G98: TEN | H98: 9 | I98: 93.2 | J98: — | K98: — | L98: Depth | N98: 🎯 R8 TARGET · High-volume slot WR. | O98: ▲ Up
A99: ☐ | B99: 97 | C99: R8 | D99: RJ Harvey | E99: RB | F99: 33 | G99: Denver Broncos | H99: 10 | I99: 93.4 | J99: 83 | K99: +5 | L99: Fair | N99: 🎯 R8 TARGET · 💤 SLEEPER — finished RB20 as a rookie; Year 2 in Payton's offense behind a top O-line, Dobbins hurt. Rookie RB; market ~R8 (expected ready Week 1). | O99: ● Role
A100: ☐ | B100: 98 | C100: R8 | D100: Sam LaPorta | E100: TE | F100: 8 | G100: Detroit Lions | H100: 6 | I100: 94.2 | J100: 84 | K100: +5 | L100: Fair | N100: 🎯 R8 TARGET · Bounce-back TE; market ~R8. | O100: ▲ Up
...

Sheet Injury & Susp. Watch
A1: Injury & Suspension Watch — updated Sept 3, 2026
A2: Only players with reported concerns are listed; an absent name is NOT confirmed healthy. Roster cuts finalize Aug 31 and Week 1 is ~Sept 7 (Rams-49ers open in Melbourne Sept 10) — re-check the morning of your draft. Red = likely to miss time / real risk; Yellow = monitor; Green = cloud cleared.
A4: Player | B4: Pos | C4: Team | D4: Type | E4: Detail | F4: Draft Impact
A5: George Kittle | B5: TE | C5: SF | D5: Injury | E5: Activated off PUP (Achilles, 2025 playoffs). 49ers confident for the Sept 10 Melbourne opener; may ease in early. | F5: Upgraded — draftable low-end TE1 again; Jake Tonges only if he sits Wk1.
A6: Puka Nacua | B6: WR | C6: LAR | D6: Suspension | E6: NOT on the commissioner's exempt list as of Sept 1; no suspension announced. Civil case pushed past Sept 7 (trial set 2028). | F6: Risk materially reduced — likely plays Wk1. Draft near cost.
A7: Josh Jacobs | B7: RB | C7: GB | D7: Injury + Suspension | E7: Placed on the NFL Commissioner's Exempt List Aug 30 (formal misdemeanor charges). Cannot practice or play; out indefinitely. | F7: Out to start the season (0-17 games, ~6 likely). Late stash only; Lloyd + Kaleb Johnson (trade) handle GB.
A8: Jordyn Tyson | B8: WR | C8: NO | D8: Injury | E8: Hamstring now expected to linger into the regular season, possibly as far as ~Week 7. | F8: Late-round dart only; Chris Olave is the beneficiary.
A9: Jeremiyah Love | B9: RB | C9: ARI | D9: Injury | E9: High ankle sprain; roughly 50/50 for Week 1 with a likely 1-2 game ramp-up. | F9: Don't draft above ~Round 4.
A10: Breece Hall | B10: RB | C10: NYJ | D10: Injury | E10: Groin; expected out ~2-3 weeks. | F10: Monitor Week 1; Braelon Allen is the handcuff.
A11: Luther Burden III | B11: WR | C11: CHI | D11: Injury | E11: Groin (Aug 8); out ~a month, hopeful for Week 1. | F11: Now clearly WR2 behind Rome Odunze; risky at ADP.
A12: Kyle Monangai | B12: RB | C12: CHI | D12: Injury | E12: Hyperextended knee; out multiple weeks. | F12: Late stash only.
A13: Zach Charbonnet | B13: RB | C13: SEA | D13: Injury | E13: ACL; on PUP, likely misses the start of the season. | F13: Late stash; Kenneth Walker's handcuff.
A14: Jayden Higgins | B14: WR | C14: HOU | D14: Injury | E14: Torn ACL — out for the season. | F14: Do not draft.
A15: Christian McCaffrey | B15: RB | C15: SF | D15: Injury | E15: Back to full practice and team drills; the camp 'tightness' was calf/load-management. Expected Wk1. | F15: Upgraded to full go; durability caveat remains (age 30, 413 touches '25).
... A30: Alvin Kamara | B30: RB | C30: NO | D30: Injury | E30: MCL sprain; NOT placed on IR, preserving an earlier return. | F30: Draft cautiously; confirm Wk1 status.

Sheet Value Picks
A1: Value Picks — experts rank these ABOVE where the fresh market (ADP) drafts them
A2: Value = market rank (fresh ADP, Aug 17-22) minus expert rank (Aug 9). Positive = board rates him higher than the market = possible discount. Check the Flag column — some gaps are injuries, not value.
A4: Player | B4: Pos | C4: Team | D4: Bye | E4: Mkt Rk | F4: ADP | G4: ADP Rd | H4: Rec Rd | I4: Exp Rk | J4: Value | K4: Flag | L4: Note
A5: Brock Bowers | B5: TE | C5: Las Vegas Raiders | D5: 13 | E5: 44 | F5: 43 | G5: 4 | H5: R3 | I5: 20 | J5: +24 | L5: Experts' TE1, ranked well above where the market drafts him (~R4). Elite TE edge if you want it.
A6: Lamar Jackson | B6: QB | C6: Baltimore Ravens | D6: 13 | E6: 59 | F6: 56.7 | G6: 5 | H6: R4 | I6: 37 | J6: +22 | L6: Experts' QB2; market waits ~R5. Wait-on-QB reward.
A7: Colston Loveland | B7: TE | C7: Chicago Bears | D7: 10 | E7: 62 | F7: 61.3 | G7: 6 | H7: R5 | I7: 41 | J7: +21 | L7: Experts high on this rookie TE (TE3); market ~R6. Rookie variance.
A8: Jordyn Tyson | B8: WR | C8: New Orleans Saints | D8: 8 | E8: 100 | F8: 126.9 | G8: 11 | H8: R9 | I8: 81 | J8: +19 | K8: Hamstring — ~2 months, misses opener | L8: INJURY: camp hamstring (~2 months, misses opener). Market already dropped him; not a value — late stash only.
A9: Jalen Hurts | B9: QB | C9: Philadelphia Eagles | D9: 10 | E9: 80 | F9: 80.9 | G9: 7 | H9: R6 | I9: 62 | J9: +18 | L9: Experts' QB5; market ~R7. Rushing-floor QB at a discount.
A10: Trey McBride | B10: TE | C10: Arizona Cardinals | D10: 14 | E10: 39 | F10: 38.2 | G10: 4 | H10: R3 | I10: 22 | J10: +17 | L10: Experts' TE2; market ~R4. Second shot at the premium-TE tier.
A11: Tucker Kraft | B11: TE | C11: Green Bay Packers | D11: 11 | E11: 91 | F11: 100.5 | G11: 9 | H11: R7 | I11: 74 | J11: +17 | L11: Value TE (experts' TE5-6); market ~R9. No injury reported.
A12: Luther Burden III | B12: WR | C12: Chicago Bears | D12: 10 | E12: 63 | F12: 61.7 | G12: 6 | H12: R6 | I12: 48 | J12: +15 | K12: Groin — ~1 month, hopeful Wk1 | L12: INJURY: groin (~1 month), hopeful Wk1. Experts rank him above market but injury adds risk.
A13: Tyler Warren | B13: TE | C13: Indianapolis Colts | D13: 13 | E13: 72 | F13: 70.4 | G13: 6 | H13: R6 | I13: 57 | J13: +15 | L13: Rookie TE experts like (TE4); market ~R6. Elite projected volume.
A14: Harold Fannin Jr. | B14: TE | C14: Cleveland Browns | D14: 11 | E14: 83 | F14: 83.8 | G14: 7 | H14: R7 | I14: 69 | J14: +14 | L14: Deep-sleeper rookie TE; experts TE5, market ~R7.
A15: Jayden Daniels | B15: QB | C15: Washington Commanders | D15: 7 | E15: 73 | F15: 71 | G15: 6 | H15: R6 | I15: 63 | J15: +10 | L15: Experts rank him ~10 spots above the market (ADP ~R6). QB value if you trust the board.
A17: Market premiums — market drafts these ahead of the expert board (fade, or risen since Aug 9)
A18: Player | B18: Pos | C18: Team | D18: Bye | E18: Mkt Rk | F18: ADP | G18: ADP Rd | H18: Rec Rd | I18: Exp Rk | J18: Value | K18: Flag | L18: Note
A19: Alec Pierce | B19: WR | C19: Indianapolis Colts | D19: 13 | E19: 58 | F19: 56.4 | G19: 5 | H19: R7 | I19: 80 | J19: -22 | K19: Off-season ankle surgery / PUP | L19: INJURY: ankle surgery/PUP, aiming for Wk1. Market drafts him ~R5 vs stale Aug-9 expert R7.
A20: Parker Washington | B20: WR | C20: Jacksonville Jaguars | D20: 7 | E20: 66 | F20: 64.7 | G20: 6 | H20: R7 | I20: 87 | J20: -21 | L20: Riser — market ~R6 vs stale expert R8.
A21: Michael Wilson | B21: WR | C21: Arizona Cardinals | D21: 14 | E21: 77 | F21: 76.1 | G21: 7 | H21: R8 | I21: 97 | J21: -20 | L21: Riser — market ~R7 vs stale expert R9.
A22: Courtland Sutton | B22: WR | C22: Denver Broncos | D22: 10 | E22: 60 | F22: 59.7 | G22: 5 | H22: R6 | I22: 78 | J22: -18 | L22: Market drafts him ~18 spots ahead of the Aug-9 expert board (ADP ~R5) — fade, or he's risen since.
A23: Rome Odunze | B23: WR | C23: Chicago Bears | D23: 10 | E23: 48 | F23: 47.3 | G23: 4 | H23: R5 | I23: 64 | J23: -16 | L23: Market drafts him ~16 spots ahead of the Aug-9 expert board (ADP ~R4) — fade, or he's risen since.
A24: Michael Pittman Jr. | B24: WR | C24: Pittsburgh Steelers | D24: 9 | E24: 81 | F24: 81 | G24: 7 | H24: R8 | I24: 96 | J24: -15 | L24: Market drafts him ~15 spots ahead of the Aug-9 expert board (ADP ~R7) — fade, or he's risen since.
A25: Jameson Williams | B25: WR | C25: Detroit Lions | D25: 6 | E25: 42 | F25: 40.4 | G25: 4 | H25: R5 | I25: 56 | J25: -14 | L25: Market drafts him ~14 spots ahead of the Aug-9 expert board (ADP ~R4) — fade, or he's risen since.
A26: Chris Godwin | B26: WR | C26: Tampa Bay Buccaneers | D26: 10 | E26: 79 | F26: 77.6 | G26: 7 | H26: R8 | I26: 93 | J26: -14 | L26: Market drafts him ~14 spots ahead of the Aug-9 expert board (ADP ~R7) — fade, or he's risen since.
A27: Zay Flowers | B27: WR | C27: Baltimore Ravens | D27: 13 | E27: 26 | F27: 25.3 | G27: 3 | H27: R3 | I27: 39 | J27: -13 | L27: Market drafts him ~13 spots ahead of the Aug-9 expert board (ADP ~R3) — fade, or he's risen since.

Sheet RB
A1: Drafted | B1: Pos Rk | C1: Rec Rd | D1: Player | E1: Ovr | F1: Team | G1: Bye | H1: ADP | I1: Value | J1: Verdict | K1: Flag | L1: Notes | M1: PPR Lean
A2: {=IFERROR(INDEX('Draft Board'!$A$2:$A$179,MATCH($D2,'Draft Board'!$D$2:$D$179,0)),"☐")} -> ☐ | B2: 1 | C2: R1 | D2: Jahmyr Gibbs | E2: 1 | F2: Detroit Lions | G2: 6 | H2: 1.5 | I2: 0 | J2: Fair | L2: [Sep 3] Workload bump: Isiah Pacheco (IR) is out to start the season, funneling more Detroit backfield work to Gibbs. 🎯 R1 TARGET · Fairly valued vs the market. Target ~R1; don't reach much earlier. | M2: ● Role
A3: {=IFERROR(INDEX('Draft Board'!$A$2:$A$179,MATCH($D3,'Draft Board'!$D$2:$D$179,0)),"☐")} -> ☐ | B3: 2 | C3: R1 | D3: Bijan Robinson | E3: 2 | F3: Atlanta Falcons | G3: 11 | H3: 2.3 | I3: 0 | J3: Fair | L3: 🎯 R1 TARGET · Fairly valued vs the market. Target ~R1; don't reach much earlier. | M3: ● Role
A4: {=IFERROR(INDEX('Draft Board'!$A$2:$A$179,MATCH($D4,'Draft Board'!$D$2:$D$179,0)),"☐")} -> ☐ | B4: 3 | C4: R1 | D4: Jonathan Taylor | E4: 5 | F4: Indianapolis Colts | G4: 13 | H4: 6 | I4: -1 | J4: Fair | L4: Fairly valued vs the market. Target ~R1; don't reach much earlier. | M4: ● Role
A5: {=IFERROR(INDEX('Draft Board'!$A$2:$A$179,MATCH($D5,'Draft Board'!$D$2:$D$179,0)),"☐")} -> ☐ | B5: 4 | C5: R1 | D5: Christian McCaffrey | E5: 6 | F5: San Francisco 49ers | G5: 8 | H5: 6.8 | I5: +1 | J5: Fair | K5: Back to full practice — Wk1 expected (age/workload watch) | L5: [Sep 3] Returned to full practice & team drills; expected to play Wk1 vs LAR. The camp 'tightness' was calf/load-management; durability caveat remains (age 30, 413 touches in '25). INJURY: missed camp with 'tightness'; age 30, injury-prone (413 touches in 2025). Elite but risky at a Round-1 price. | M5: ● Role
A6: {=IFERROR(INDEX('Draft Board'!$A$2:$A$179,MATCH($D6,'Draft Board'!$D$2:$D$179,0)),"☐")} -> ☐ | B6: 5 | C6: R1 | D6: James Cook | E6: 8 | F6: Buffalo Bills | G6: 7 | H6: 9.2 | I6: -1 | J6: Fair | L6: Fairly valued vs the market. Target ~R1; don't reach much earlier. | M6: ● Role
A7: {=IFERROR(INDEX('Draft Board'!$A$2:$A$179,MATCH($D7,'Draft Board'!$D$2:$D$179,0)),"☐")} -> ☐ | B7: 6 | C7: R1 | D7: De'Von Achane | E7: 9 | F7: Miami Dolphins | G7: 6 | H7: 11.5 | I7: -2 | J7: Fair | L7: Fairly valued vs the market. Target ~R1; don't reach much earlier. | M7: ● Role
A8: {=IFERROR(INDEX('Draft Board'!$A$2:$A$179,MATCH($D8,'Draft Board'!$D$2:$D$179,0)),"☐")} -> ☐ | B8: 7 | C8: R2 | D8: Derrick Henry | E8: 12 | F8: Baltimore Ravens | G8: 13 | H8: 9.9 | I8: -7 | J8: OVERVALUED | L8: Fairly valued vs the market. Target ~R2; don't reach much earlier. | M8: ● Role
A9: {=IFERROR(INDEX('Draft Board'!$A$2:$A$179,MATCH($D9,'Draft Board'!$D$2:$D$179,0)),"☐")} -> ☐ | B9: 8 | C9: R2 | D9: Ashton Jeanty | E9: 15 | F9: Las Vegas Raiders | G9: 13 | H9: 15.1 | I9: +4 | J9: Fair | K9: Ankle — made 53-man, no return date; monitor | L9: [Sep 3] Ankle injury: made the 53-man roster but the Raiders set no return date — a real Wk1 risk at a Round-2 price. Mike Washington Jr. is the contingency. Fairly valued vs the market. Target ~R2; don't reach much earlier. | M9: ● Role
A10: {=IFERROR(INDEX('Draft Board'!$A$2:$A$179,MATCH($D10,'Draft Board'!$D$2:$D$179,0)),"☐")} -> ☐ | B10: 9 | C10: R2 | D10: Chase Brown | E10: 16 | F10: Cincinnati Bengals | G10: 6 | H10: 15.1 | I10: 0 | J10: Fair | L10: Fairly valued vs the market. Target ~R2; don't reach much earlier. | M10: ● Role
A11: {=IFERROR(INDEX('Draft Board'!$A$2:$A$179,MATCH($D11,'Draft Board'!$D$2:$D$179,0)),"☐")} -> ☐ | B11: 10 | C11: R2 | D11: Saquon Barkley | E11: 18 | F11: Philadelphia Eagles | G11: 10 | H11: 17.3 | I11: +4 | J11: Fair | L11: Fairly valued vs the market. Target ~R2; don't reach much earlier. | M11: ● Role
A12: {=IFERROR(INDEX('Draft Board'!$A$2:$A$179,MATCH($D12,'Draft Board'!$D$2:$D$179,0)),"☐")} -> ☐ | B12: 11 | C12: R2 | D12: Kenneth Walker III | E12: 22 | F12: Kansas City Chiefs | G12: 5 | H12: 21.6 | I12: +3 | J12: Fair | L12: Fairly valued vs the market. Target ~R2; don't reach much earlier. | M12: ● Role
A13: {=IFERROR(INDEX('Draft Board'!$A$2:$A$179,MATCH($D13,'Draft Board'!$D$2:$D$179,0)),"☐")} -> ☐ | B13: 12 | C13: R2 | D13: Omarion Hampton | E13: 23 | F13: Los Angeles Chargers | G13: 7 | H13: 23.6 | I13: +2 | J13: Fair | L13: Fairly valued vs the market. Target ~R2; don't reach much earlier. | M13: ● Role
A14: {=IFERROR(INDEX('Draft Board'!$A$2:$A$179,MATCH($D14,'Draft Board'!$D$2:$D$179,0)),"☐")} -> ☐ | B14: 13 | C14: R3 | D14: Kyren Williams | E14: 26 | F14: Los Angeles Rams | G14: 11 | H14: 27 | I14: -3 | J14: Fair | L14: 🎯 R2 TARGET · Fairly valued vs the market. Target ~R3; don't reach much earlier. | M14: ● Role
A15: {=IFERROR(INDEX('Draft Board'!$A$2:$A$179,MATCH($D15,'Draft Board'!$D$2:$D$179,0)),"☐")} -> ☐ | B15: 14 | C15: R3 | D15: Javonte Williams | E15: 32 | F15: Dallas Cowboys | G15: 14 | H15: 33.6 | I15: 0 | J15: Fair | L15: Fairly valued vs the market. Target ~R3; don't reach much earlier. | M15: ● Role
A16: {=IFERROR(INDEX('Draft Board'!$A$2:$A$179,MATCH($D16,'Draft Board'!$D$2:$D$179,0)),"☐")} -> ☐ | B16: 15 | C16: R4 | D16: Josh Jacobs | E16: 36 | F16: Green Bay Packers | G16: 11 | H16: 24.9 | I16: -6 | J16: OVERVALUED | K16: ON COMMISSIONER'S EXEMPT LIST (Aug 30) — out indefinitely | L16: [Sep 3] Placed on the NFL Commissioner's Exempt List Aug 30 (formal misdemeanor charges) — cannot practice or play; out indefinitely to start the season (games-missed range 0-17, ~6 most likely). Draft only as a late stash. GB backfield now MarShawn Lloyd + newly traded-for Kaleb Johnson. INJURY + SUSPENSION: camp groin, plus a possible suspension (May arrest) still under review. Double risk; MarShawn Lloyd is the handcuff. | M16: ● Role
A17: {=IFERROR(INDEX('Draft Board'!$A$2:$A$179,MATCH($D17,'Draft Board'!$D$2:$D$179,0)),"☐")} -> ☐ | B17: 16 | C17: R4 | D17: Jeremiyah Love | E17: 37 | F17: Arizona Cardinals | G17: 14 | H17: 30 | I17: +2 | J17: Fair | K17: High ankle sprain — ~50/50 for Wk1 | L17: INJURY: high ankle sprain, ~50/50 for Week 1 with a 1-2 game ramp. Don't draft above ~Round 4. | M17: ● Role
A18: {=IFERROR(INDEX('Draft Board'!$A$2:$A$179,MATCH($D18,'Draft Board'!$D$2:$D$179,0)),"☐")} -> ☐ | B18: 17 | C18: R4 | D18: Cam Skattebo | E18: 38 | F18: New York Giants | G18: 8 | H18: 34.3 | I18: -8 | J18: OVERVALUED | L18: Fairly valued vs the market. Target ~R4; don't reach much earlier. | M18: ● Role
A19: {=IFERROR(INDEX('Draft Board'!$A$2:$A$179,MATCH($D19,'Draft Board'!$D$2:$D$179,0)),"☐")} -> ☐ | B19: 18 | C19: R4 | D19: Breece Hall | E19: 39 | F19: New York Jets | G19: 13 | H19: 34.9 | I19: +4 | J19: Fair | K19: Groin — ~2-3 weeks | L19: INJURY: groin, out ~2-3 weeks. Monitor Week 1; Braelon Allen is the handcuff. | M19: ● Role
A20: {=IFERROR(INDEX('Draft Board'!$A$2:$A$179,MATCH($D20,'Draft Board'!$D$2:$D$179,0)),"☐")} -> ☐ | B20: 19 | C20: R4 | D20: Travis Etienne Jr. | E20: 42 | F20: New Orleans Saints | G20: 8 | H20: 40.1 | I20: +3 | J20: Fair | L20: Fairly valued vs the market. Target ~R4; don't reach much earlier. | M20: ● Role
A21: {=IFERROR(INDEX('Draft Board'!$A$2:$A$179,MATCH($D21,'Draft Board'!$D$2:$D$179,0)),"☐")} -> ☐ | B21: 20 | C21: R4 | D21: Bucky Irving | E21: 44 | F21: Tampa Bay Buccaneers | G21: 10 | H21: 45.5 | I21: +3 | J21: Fair | L21: Fairly valued vs the market. Target ~R4; don't reach much earlier. | M21: ● Role
A22: {=IFERROR(INDEX('Draft Board'!$A$2:$A$179,MATCH($D22,'Draft Board'!$D$2:$D$179,0)),"☐")} -> ☐ | B22: 21 | C22: R5 | D22: D'Andre Swift | E22: 48 | F22: Chicago Bears | G22: 10 | H22: 43.3 | I22: -7 | J22: OVERVALUED | K22: Bigger role — Monangai (knee) out weeks | L22: [Sep 3] Value bump: Kyle Monangai's hyperextended knee opens a larger early-down role for Swift to start the year. 🎯 R4 TARGET · Fairly valued vs the market. Target ~R5; don't reach much earlier. | M22: ● Role
A23: {=IFERROR(INDEX('Draft Board'!$A$2:$A$179,MATCH($D23,'Draft Board'!$D$2:$D$179,0)),"☐")} -> ☐ | B23: 22 | C23: R5 | D23: Quinshon Judkins | E23: 52 | F23: Cleveland Browns | G23: 11 | H23: 51.4 | I23: +4 | J23: Fair | L23: 🎯 R5 TARGET · Fairly valued vs the market. Target ~R5; don't reach much earlier. | M23: ● Role
A24: {=IFERROR(INDEX('Draft Board'!$A$2:$A$179,MATCH($D24,'Draft Board'!$D$2:$D$179,0)),"☐")} -> ☐ | B24: 23 | C24: R5 | D24: Bhayshul Tuten | E24: 54 | F24: Jacksonville Jaguars | G24: 7 | H24: 53.4 | I24: -8 | J24: OVERVALUED | L24: 💤 SLEEPER — big-play rookie with a clear path to JAX RB2/flex value; league-winner upside. Fairly valued vs the market. Target ~R5; don't reach much earlier. | M24: ● Role
A25: {=IFERROR(INDEX('Draft Board'!$A$2:$A$179,MATCH($D25,'Draft Board'!$D$2:$D$179,0)),"☐")} -> ☐ | B25: 24 | C25: R5 | D25: David Montgomery | E25: 56 | F25: Houston Texans | G25: 8 | H25: 55 | I25: +4 | J25: Fair | L25: Fairly valued vs the market. Target ~R5; don't reach much earlier. | M25: ● Role
A26: {=IFERROR(INDEX('Draft Board'!$A$2:$A$179,MATCH($D26,'Draft Board'!$D$2:$D$179,0)),"☐")} -> ☐ | B26: 25 | C26: R5 | D26: TreVeyon Henderson | E26: 59 | F26: New England Patriots | G26: 11 | H26: 60.2 | I26: +8 | J26: UNDERVALUED | L26: 💤 SLEEPER — elite explosiveness + receiving; breakout if he takes the NE backfield from Stevenson. Fairly valued vs the market. Target ~R5; don't reach much earlier. | M26: ● Role
A27: {=IFERROR(INDEX('Draft Board'!$A$2:$A$179,MATCH($D27,'Draft Board'!$D$2:$D$179,0)),"☐")} -> ☐ | B27: 26 | C27: R6 | D27: Jaylen Warren | E27: 63 | F27: Pittsburgh Steelers | G27: 9 | H27: 63.1 | I27: -1 | J27: Fair | L27: 💤 SLEEPER — PIT committee with real standalone value; smash play if Dowdle misses time. Fairly valued vs the market. Target ~R6; don't reach much earlier. | M27: ● Role
A28: {=IFERROR(INDEX('Draft Board'!$A$2:$A$179,MATCH($D28,'Draft Board'!$D$2:$D$179,0)),"☐")} -> ☐ | B28: 27 | C28: R6 | D28: Tony Pollard | E28: 66 | F28: Tennessee Titans | G28: 9 | H28: 66.1 | I28: +1 | J28: Fair | L28: Fairly valued vs the market. Target ~R6; don't reach much earlier. | M28: ● Role
A29: {=IFERROR(INDEX('Draft Board'!$A$2:$A$179,MATCH($D29,'Draft Board'!$D$2:$D$179,0)),"☐")} -> ☐ | B29: 28 | C29: R6 | D29: Rhamondre Stevenson | E29: 67 | F29: New England Patriots | G29: 11 | H29: 68.5 | I29: -1 | J29: Fair | L29: Fairly valued vs the market. Target ~R6; don't reach much earlier. | M29: ● Role
A30: {=IFERROR(INDEX('Draft Board'!$A$2:$A$179,MATCH($D30,'Draft Board'!$D$2:$D$179,0)),"☐")} -> ☐ | B30: 29 | C30: R6 | D30: Jadarian Price | E30: 72 | F30: Seattle Seahawks | G30: 11 | H30: 75.3 | I30: +9 | J30: UNDERVALUED | K30: SEA lead back — Charbonnet (IR) out ~4 wks | L30: [Sep 3] With Zach Charbonnet on IR (~first 4 games), rookie Price is positioned to lead the Seattle backfield — startable sleeper; George Holani handles passing downs. 🎯 R6 TARGET · 💤 SLEEPER — first-round rookie workhorse in a strong SEA run game; immediate volume. Fairly valued vs the market. Target ~R6; don't reach much earlier. | M30: ● Role
A31: {=IFERROR(INDEX('Draft Board'!$A$2:$A$179,MATCH($D31,'Draft Board'!$D$2:$D$179,0)),"☐")} -> ☐ | B31: 30 | C31: R7 | D31: Rico Dowdle | E31: 77 | F31: Pittsburgh Steelers | G31: 9 | H31: 74.6 | I31: +3 | J31: Fair | L31: 🎯 R7 TARGET · 💤 SLEEPER — splitting first-team reps in PIT; high-value touches at ~R7 cost. Fairly valued vs the market. Target ~R7; don't reach much earlier. | M31: ● Role
A32: {=IFERROR(INDEX('Draft Board'!$A$2:$A$179,MATCH($D32,'Draft Board'!$D$2:$D$179,0)),"☐")} -> ☐ | B32: 31 | C32: R7 | D32: Chuba Hubbard | E32: 78 | F32: Carolina Panthers | G32: 5 | H32: 77.6 | I32: +2 | J32: Fair | K32: Hamstring — committee w/ Brooks | L32: INJURY: hamstring, week-to-week; committee with Jonathon Brooks to start. Reduced ceiling. | M32: ● Role
A33: {=IFERROR(INDEX('Draft Board'!$A$2:$A$179,MATCH($D33,'Draft Board'!$D$2:$D$179,0)),"☐")} -> ☐ | B33: 32 | C33: R7 | D33: J.K. Dobbins | E33: 81 | F33: Denver Broncos | G33: 10 | H33: 83.3 | I33: -3 | J33: Fair | K33: Soft-tissue — may start slow | L33: INJURY: soft-tissue (hamstring); extensive injury history. Jonah Coleman could compete — slow-start/committee risk. | M33: ● Role
A34: {=IFERROR(INDEX('Draft Board'!$A$2:$A$179,MATCH($D34,'Draft Board'!$D$2:$D$179,0)),"☐")} -> ☐ | B34: 33 | C34: R8 | D34: RJ Harvey | E34: 97 | F34: Denver Broncos | G34: 10 | H34: 93.4 | I34: +5 | J34: Fair | L34: 🎯 R8 TARGET · 💤 SLEEPER — finished RB20 as a rookie; Year 2 in Payton's offense behind a top O-line, Dobbins hurt. Rookie RB; market ~R8 (expected ready Week 1). | M34: ● Role
A35: {=IFERROR(INDEX('Draft Board'!$A$2:$A$179,MATCH($D35,'Draft Board'!$D$2:$D$179,0)),"☐")} -> ☐ | B35: 34 | C35: R8 | D35: Blake Corum | E35: 103 | F35: Los Angeles Rams | G35: 11 | H35: 119.8 | I35: +2 | J35: Fair | L35: 🎯 HANDCUFF · Kyren Williams' backup with standalone flex value + RB1 upside — top handcuff to target (~R10). | M35: ● Role
A36: {=IFERROR(INDEX('Draft Board'!$A$2:$A$179,MATCH($D36,'Draft Board'!$D$2:$D$179,0)),"☐")} -> ☐ | B36: 35 | C36: R9 | D36: Jonathon Brooks | E36: 105 | F36: CAR | G36: 5 | H36: 97.1 | I36: — | J36: Depth | K36: ACL history; rising in committee | L36: 🎯 R9 TARGET · 💤 SLEEPER — lead-role upside in a CAR committee (twice-torn ACL is the risk). INJURY: twice-torn ACL (3 games in 2 yrs). Rising in a committee with Hubbard — upside stash with real risk. | M36: ● Role
A37: {=IFERROR(INDEX('Draft Board'!$A$2:$A$179,MATCH($D37,'Draft Board'!$D$2:$D$179,0)),"☐")} -> ☐ | B37: 36 | C37: R9 | D37: Kenny Gainwell | E37: 106 | F37: TB | G37: 10 | H37: 100.1 | I37: — | J37: Depth | L37: Pass-catching depth RB / flex. | M37: ● Role
A38: {=IFERROR(INDEX('Draft Board'!$A$2:$A$179,MATCH($D38,'Draft Board'!$D$2:$D$179,0)),"☐")} -> ☐ | B38: 37 | C38: R9 | D38: Kyle Monangai | E38: 110 | F38: Chicago Bears | G38: 10 | H38: 101.8 | I38: +6 | J38: UNDERVALUED | K38: Hyperextended knee — out multiple weeks; Wk1 in doubt | L38: [Sep 3] Hyperextended knee; expected to miss multiple weeks, Wk1 in doubt (Swift benefits). INJURY: hyperextended knee, out multiple weeks. Late stash only. | M38: ● Role
A39: {=IFERROR(INDEX('Draft Board'!$A$2:$A$179,MATCH($D39,'Draft Board'!$D$2:$D$179,0)),"☐")} -> ☐ | B39: 38 | C39: R9 | D39: Jacory Croskey-Merritt | E39: 114 | F39: WAS | G39: 7 | H39: 105 | I39: — | J39: Depth | L39: 🎯 R9 TARGET · WAS backfield committee; upside. | M39: ● Role
A40: {=IFERROR(INDEX('Draft Board'!$A$2:$A$179,MATCH($D40,'Draft Board'!$D$2:$D$179,0)),"☐")} -> ☐ | B40: 39 | C40: R9 | D40: Aaron Jones Sr. | E40: 115 | F40: MIN | G40: 6 | H40: 105.4 | I40: — | J40: Depth | L40: Split with Jordan Mason; PPR value. | M40: ● Role
A41: {=IFERROR(INDEX('Draft Board'!$A$2:$A$179,MATCH($D41,'Draft Board'!$D$2:$D$179,0)),"☐")} -> ☐ | B41: 40 | C41: R10 | D41: Jordan Mason | E41: 125 | F41: MIN | G41: 6 | H41: 115.5 | I41: — | J41: Depth | L41: 🎯 R11 TARGET · 💤 SLEEPER — standalone flex value splitting with Aaron Jones in MIN. Behind Aaron Jones; standalone flex. | M41: ● Role
A42: {=IFERROR(INDEX('Draft Board'!$A$2:$A$179,MATCH($D42,'Draft Board'!$D$2:$D$179,0)),"☐")} -> ☐ | B42: 41 | C42: R11 | D42: Rachaad White | E42: 129 | F42: WAS | G42: 7 | H42: 121.8 | I42: — | J42: Depth | L42: Pass-catching RB; flex. | M42: ● Role
A43: {=IFERROR(INDEX('Draft Board'!$A$2:$A$179,MATCH($D43,'Draft Board'!$D$2:$D$179,0)),"☐")} -> ☐ | B43: 42 | C43: R11 | D43: Zach Charbonnet | E43: 133 | F43: SEA | G43: 11 | H43: 131.3 | I43: — | J43: Depth | K43: On IR — out ~first 4 games | L43: [Sep 3] On IR, expected to miss ~the first 4 games; rookie Jadarian Price leads the SEA backfield in his absence. INJURY: ACL, on PUP — likely misses the start of the season. Late stash; Kenneth Walker's handcuff. | M43: ● Role
A44: {=IFERROR(INDEX('Draft Board'!$A$2:$A$179,MATCH($D44,'Draft Board'!$D$2:$D$179,0)),"☐")} -> ☐ | B44: 43 | C44: R12 | D44: Woody Marks | E44: 149 | F44: HOU | G44: 8 | H44: 139.2 | I44: — | J44: Depth | L44: 🎯 R13 TARGET · HOU rookie RB; safer late option. | M44: ● Role
A45: {=IFERROR(INDEX('Draft Board'!$A$2:$A$179,MATCH($D45,'Draft Board'!$D$2:$D$179,0)),"☐")} -> ☐ | B45: 44 | C45: R12 | D45: Tyjae Spears | E45: 152 | F45: TEN | G45: 9 | H45: 140.1 | I45: — | J45: Depth | L45: Tony Pollard backup / handcuff. | M45: ● Role
A46: {=IFERROR(INDEX('Draft Board'!$A$2:$A$179,MATCH($D46,'Draft Board'!$D$2:$D$179,0)),"☐")} -> ☐ | B46: 45 | C46: R13 | D46: Alvin Kamara | E46: 161 | F46: NO | G46: 8 | H46: 147.2 | I46: — | J46: Depth | K46: MCL sprain — not on IR; draft cautiously | L46: [Sep 3] MCL sprain; the Saints did NOT place him on IR (preserving an earlier return), but draft cautiously and confirm his Wk1 status. Aging but still gets touches; flex. | M46: ● Role
A47: {=IFERROR(INDEX('Draft Board'!$A$2:$A$179,MATCH($D47,'Draft Board'!$D$2:$D$179,0)),"☐")} -> ☐ | B47: 46 | C47: R13 | D47: Tank Bigsby | E47: 168 | F47: PHI | G47: 10 | H47: 152.8 | I47: — | J47: Depth | L47: 🎯 HANDCUFF · Saquon Barkley's backup — league-winner upside if Saquon misses time (~R13). | M47: ● Role
A48: {=IFERROR(INDEX('Draft Board'!$A$2:$A$179,MATCH($D48,'Draft Board'!$D$2:$D$179,0)),"☐")} -> ☐ | B48: 47 | C48: R14 | D48: Isiah Pacheco | E48: 172 | F48: DET | G48: 6 | H48: 156.6 | I48: — | J48: Depth | K48: On IR (MCL) — out to start; Gibbs benefits | L48: [Sep 3] Now on IR (MCL) — out of the Detroit backfield to start the year, which boosts Jahmyr Gibbs. 🎯 HANDCUFF (Gibbs) · Detroit backup to your 1.01 pick — sprained MCL (monitor); David Montgomery also soaks up work if Gibbs misses time. | M48: ● Role
A49: {=IFERROR(INDEX('Draft Board'!$A$2:$A$179,MATCH($D49,'Draft Board'!$D$2:$D$179,0)),"☐")} -> ☐ | B49: 48 | C49: R14 | D49: MarShawn Lloyd | E49: 174 | F49: GB | G49: 11 | H49: 160.1 | I49: — | J49: Depth | K49: GB touches w/ Jacobs out — but shares w/ K.Johnson | L49: [Sep 3] In line for Green Bay touches with Jacobs on the exempt list, but GB traded for Kaleb Johnson — expect a committee. Speculative upside stash. Josh Jacobs handcuff — upside if Jacobs misses time. | M49: ● Role
A50: {=IFERROR(INDEX('Draft Board'!$A$2:$A$179,MATCH($D50,'Draft Board'!$D$2:$D$179,0)),"☐")} -> ☐ | B50: 49 | C50: R15 | D50: Braelon Allen | E50: 177 | F50: NYJ | G50: 13 | H50: 171.3 | I50: — | J50: Depth | L50: Breece Hall handcuff. | M50: ● Role
A51: {=IFERROR(INDEX('Draft Board'!$A$2:$A$179,MATCH($D51,'Draft Board'!$D$2:$D$179,0)),"☐")} -> ☐ | B51: 50 | C51: R15 | D51: Mike Washington Jr. | E51: 178 | F51: Las Vegas Raiders | G51: 13 | H51: 185 | I51: — | J51: — | L51: 🎯 R15 TARGET · Ashton Jeanty's rookie handcuff (LV); Jeanty banged up — league-winner upside if he misses time. Essentially undrafted, last-round flier. | M51: ● Role

Sheet WR
A1: Drafted | B1: Pos Rk | C1: Rec Rd | D1: Player | E1: Ovr | F1: Team | G1: Bye | H1: ADP | I1: Value | J1: Verdict | K1: Flag | L1: Notes | M1: PPR Lean
A2: {=IFERROR(INDEX('Draft Board'!$A$2:$A$179,MATCH($D2,'Draft Board'!$D$2:$D$179,0)),"☐")} -> ☐ | B2: 1 | C2: R1 | D2: Ja'Marr Chase | E2: 3 | F2: Cincinnati Bengals | G2: 6 | H2: 3.9 | I2: +1 | J2: Fair | L2: 🎯 R1 TARGET · Fairly valued vs the market. Target ~R1; don't reach much earlier. | M2: ▲ Up
A3: {=IFERROR(INDEX('Draft Board'!$A$2:$A$179,MATCH($D3,'Draft Board'!$D$2:$D$179,0)),"☐")} -> ☐ | B3: 2 | C3: R1 | D3: Jaxon Smith-Njigba | E3: 4 | F3: Seattle Seahawks | G3: 11 | H3: 5.4 | I3: 0 | J3: Fair | L3: Fairly valued vs the market. Target ~R1; don't reach much earlier. | M3: ▲ Up
A4: {=IFERROR(INDEX('Draft Board'!$A$2:$A$179,MATCH($D4,'Draft Board'!$D$2:$D$179,0)),"☐")} -> ☐ | B4: 3 | C4: R1 | D4: Amon-Ra St. Brown | E4: 7 | F4: Detroit Lions | G4: 6 | H4: 7.9 | I4: 0 | J4: Fair | L4: Fairly valued vs the market. Target ~R1; don't reach much earlier. | M4: ▲ Up
A5: {=IFERROR(INDEX('Draft Board'!$A$2:$A$179,MATCH($D5,'Draft Board'!$D$2:$D$179,0)),"☐")} -> ☐ | B5: 4 | C5: R1 | D5: CeeDee Lamb | E5: 10 | F5: Dallas Cowboys | G5: 14 | H5: 12.5 | I5: +4 | J5: Fair | L5: Fairly valued vs the market. Target ~R1; don't reach much earlier. | M5: ▲ Up
A6: {=IFERROR(INDEX('Draft Board'!$A$2:$A$179,MATCH($D6,'Draft Board'!$D$2:$D$179,0)),"☐")} -> ☐ | B6: 5 | C6: R2 | D6: Puka Nacua | E6: 11 | F6: Los Angeles Rams | G6: 11 | H6: 3.1 | I6: -1 | J6: Fair | K6: Not on exempt list (Sep 1) — likely Wk1; small lingering risk | L6: [Sep 3] NOT placed on the commissioner's exempt list as of Sep 1 and no suspension announced; civil case pushed past Sep 7. Suspension risk is materially reduced — likely plays Wk1. SUSPENSION RISK: under NFL review; missing the Sept 10 Melbourne opener is 'on the table,' no ruling as of Aug 27. Elite when active — price in games-missed risk. | M6: ▲ Up
A7: {=IFERROR(INDEX('Draft Board'!$A$2:$A$179,MATCH($D7,'Draft Board'!$D$2:$D$179,0)),"☐")} -> ☐ | B7: 6 | C7: R2 | D7: Drake London | E7: 13 | F7: Atlanta Falcons | G7: 11 | H7: 12.4 | I7: -3 | J7: Fair | L7: Fairly valued vs the market. Target ~R2; don't reach much earlier. | M7: ▲ Up
A8: {=IFERROR(INDEX('Draft Board'!$A$2:$A$179,MATCH($D8,'Draft Board'!$D$2:$D$179,0)),"☐")} -> ☐ | B8: 7 | C8: R2 | D8: Justin Jefferson | E8: 14 | F8: Minnesota Vikings | G8: 6 | H8: 14.1 | I8: +2 | J8: Fair | L8: Fairly valued vs the market. Target ~R2; don't reach much earlier. | M8: ▲ Up
A9: {=IFERROR(INDEX('Draft Board'!$A$2:$A$179,MATCH($D9,'Draft Board'!$D$2:$D$179,0)),"☐")} -> ☐ | B9: 8 | C9: R2 | D9: Rashee Rice | E9: 17 | F9: Kansas City Chiefs | G9: 5 | H9: 15.9 | I9: -9 | J9: OVERVALUED | K9: CLEARED — NFL closed investigation (Apr 2026), no discipline | L9: [Sep 3] Fully clear: the NFL closed its personal-conduct investigation in April 2026 with no discipline. Available Wk1. SUSPENSION (cleared): off-field matter reported settled, not expected to be suspended. Treat as clear; monitor. | M9: ▲ Up
A10: {=IFERROR(INDEX('Draft Board'!$A$2:$A$179,MATCH($D10,'Draft Board'!$D$2:$D$179,0)),"☐")} -> ☐ | B10: 9 | C10: R2 | D10: A.J. Brown | E10: 19 | F10: New England Patriots | G10: 11 | H10: 19.6 | I10: +1 | J10: Fair | L10: Fairly valued vs the market. Target ~R2; don't reach much earlier. | M10: ▲ Up
A11: {=IFERROR(INDEX('Draft Board'!$A$2:$A$179,MATCH($D11,'Draft Board'!$D$2:$D$179,0)),"☐")} -> ☐ | B11: 10 | C11: R2 | D11: George Pickens | E11: 20 | F11: Dallas Cowboys | G11: 14 | H11: 19.6 | I11: -4 | J11: Fair | L11: Fairly valued vs the market. Target ~R2; don't reach much earlier. | M11: ▲ Up
A12: {=IFERROR(INDEX('Draft Board'!$A$2:$A$179,MATCH($D12,'Draft Board'!$D$2:$D$179,0)),"☐")} -> ☐ | B12: 11 | C12: R2 | D12: Nico Collins | E12: 21 | F12: Houston Texans | G12: 8 | H12: 21.5 | I12: -2 | J12: Fair | L12: Fairly valued vs the market. Target ~R2; don't reach much earlier. | M12: ▲ Up
A13: {=IFERROR(INDEX('Draft Board'!$A$2:$A$179,MATCH($D13,'Draft Board'!$D$2:$D$179,0)),"☐")} -> ☐ | B13: 12 | C13: R3 | D13: Chris Olave | E13: 24 | F13: New Orleans Saints | G13: 8 | H13: 23.9 | I13: -4 | J13: Fair | L13: 🎯 R2 TARGET · Riser — benefits if Tyson misses; worth late R2 / early R3. | M13: ▲ Up
A14: {=IFERROR(INDEX('Draft Board'!$A$2:$A$179,MATCH($D14,'Draft Board'!$D$2:$D$179,0)),"☐")} -> ☐ | B14: 13 | C14: R3 | D14: Zay Flowers | E14: 25 | F14: Baltimore Ravens | G14: 13 | H14: 25.3 | I14: -13 | J14: OVERVALUED | L14: 🎯 R2 TARGET · Market drafts him ~13 spots ahead of the Aug-9 expert board (ADP ~R3) — fade, or he's risen since. | M14: ▲ Up
A15: {=IFERROR(INDEX('Draft Board'!$A$2:$A$179,MATCH($D15,'Draft Board'!$D$2:$D$179,0)),"☐")} -> ☐ | B15: 14 | C15: R3 | D15: Malik Nabers | E15: 27 | F15: New York Giants | G15: 8 | H15: 28.2 | I15: -1 | J15: Fair | K15: Post-ACL — ramping to Wk1, top-10 upside | L15: [Sep 3] ACL recovery on track; ramping up in practice, experts eyeing a top-10 WR finish and ADP trending up. Confirm full team-drill participation before Wk1. 🎯 R3 TARGET · INJURY: post-ACL, back at practice, on track for Week 1 (worst case miss 1-2). Trending up — possible value. | M15: ▲ Up
A16: {=IFERROR(INDEX('Draft Board'!$A$2:$A$179,MATCH($D16,'Draft Board'!$D$2:$D$179,0)),"☐")} -> ☐ | B16: 15 | C16: R3 | D16: Garrett Wilson | E16: 28 | F16: New York Jets | G16: 13 | H16: 31.4 | I16: -10 | J16: OVERVALUED | L16: 🎯 R3 TARGET · Fairly valued vs the market. Target ~R3; don't reach much earlier. | M16: ▲ Up
A17: {=IFERROR(INDEX('Draft Board'!$A$2:$A$179,MATCH($D17,'Draft Board'!$D$2:$D$179,0)),"☐")} -> ☐ | B17: 16 | C17: R3 | D17: DeVonta Smith | E17: 29 | F17: Philadelphia Eagles | G17: 10 | H17: 32 | I17: -5 | J17: Fair | L17: 🎯 R3 TARGET · Fairly valued vs the market. Target ~R3; don't reach much earlier. | M17: ▲ Up
A18: {=IFERROR(INDEX('Draft Board'!$A$2:$A$179,MATCH($D18,'Draft Board'!$D$2:$D$179,0)),"☐")} -> ☐ | B18: 17 | C18: R3 | D18: Tetairoa McMillan | E18: 30 | F18: Carolina Panthers | G18: 5 | H18: 32.2 | I18: -3 | J18: Fair | L18: Fairly valued vs the market. Target ~R3; don't reach much earlier. | M18: ▲ Up
A19: {=IFERROR(INDEX('Draft Board'!$A$2:$A$179,MATCH($D19,'Draft Board'!$D$2:$D$179,0)),"☐")} -> ☐ | B19: 18 | C19: R3 | D19: Tee Higgins | E19: 33 | F19: Cincinnati Bengals | G19: 6 | H19: 36.5 | I19: +5 | J19: Fair | L19: Fairly valued vs the market. Target ~R3; don't reach much earlier. | M19: ▲ Up
A20: {=IFERROR(INDEX('Draft Board'!$A$2:$A$179,MATCH($D20,'Draft Board'!$D$2:$D$179,0)),"☐")} -> ☐ | B20: 19 | C20: R4 | D20: Emeka Egbuka | E20: 40 | F20: Tampa Bay Buccaneers | G20: 10 | H20: 34.9 | I20: -5 | J20: Fair | K20: Toe — Wk1 status uncertain | L20: 💤 SLEEPER — ascending target share in TB; efficient rookie profile (monitor toe). INJURY: toe, Week 1 status uncertain. Monitor before starting. | M20: ▲ Up
A21: {=IFERROR(INDEX('Draft Board'!$A$2:$A$179,MATCH($D21,'Draft Board'!$D$2:$D$179,0)),"☐")} -> ☐ | B21: 20 | C21: R4 | D21: Davante Adams | E21: 41 | F21: Los Angeles Rams | G21: 11 | H21: 38.4 | I21: -9 | J21: OVERVALUED | L21: Fairly valued vs the market. Target ~R4; don't reach much earlier. | M21: ▲ Up
A22: {=IFERROR(INDEX('Draft Board'!$A$2:$A$179,MATCH($D22,'Draft Board'!$D$2:$D$179,0)),"☐")} -> ☐ | B22: 21 | C22: R4 | D22: Ladd McConkey | E22: 43 | F22: Los Angeles Chargers | G22: 7 | H22: 41.2 | I22: -2 | J22: Fair | L22: Fairly valued vs the market. Target ~R4; don't reach much earlier. | M22: ▲ Up
A23: {=IFERROR(INDEX('Draft Board'!$A$2:$A$179,MATCH($D23,'Draft Board'!$D$2:$D$179,0)),"☐")} -> ☐ | B23: 22 | C23: R4 | D23: Jaylen Waddle | E23: 45 | F23: Denver Broncos | G23: 10 | H23: 47.7 | I23: +3 | J23: Fair | L23: Fairly valued vs the market. Target ~R4; don't reach much earlier. | M23: ▲ Up
A24: {=IFERROR(INDEX('Draft Board'!$A$2:$A$179,MATCH($D24,'Draft Board'!$D$2:$D$179,0)),"☐")} -> ☐ | B24: 23 | C24: R5 | D24: Jameson Williams | E24: 47 | F24: Detroit Lions | G24: 6 | H24: 40.4 | I24: -14 | J24: OVERVALUED | L24: Market drafts him ~14 spots ahead of the Aug-9 expert board (ADP ~R4) — fade, or he's risen since. | M24: ▲ Up
A25: {=IFERROR(INDEX('Draft Board'!$A$2:$A$179,MATCH($D25,'Draft Board'!$D$2:$D$179,0)),"☐")} -> ☐ | B25: 24 | C25: R5 | D25: Terry McLaurin | E25: 49 | F25: Washington Commanders | G25: 7 | H25: 45 | I25: -8 | J25: OVERVALUED | L25: 🎯 R4 TARGET · Fairly valued vs the market. Target ~R5; don't reach much earlier. | M25: ▲ Up
A26: {=IFERROR(INDEX('Draft Board'!$A$2:$A$179,MATCH($D26,'Draft Board'!$D$2:$D$179,0)),"☐")} -> ☐ | B26: 25 | C26: R5 | D26: Rome Odunze | E26: 50 | F26: Chicago Bears | G26: 10 | H26: 47.3 | I26: -16 | J26: OVERVALUED | L26: 🎯 R4 TARGET · 💤 SLEEPER — clear Bears WR1 with Burden hurt; target-share breakout. Bump up — clearly the Bears' WR1 with Burden hurt. | M26: ▲ Up
A27: {=IFERROR(INDEX('Draft Board'!$A$2:$A$179,MATCH($D27,'Draft Board'!$D$2:$D$179,0)),"☐")} -> ☐ | B27: 26 | C27: R5 | D27: D.J. Moore | E27: 51 | F27: Buffalo Bills | G27: 7 | H27: 50.6 | I27: -10 | J27: OVERVALUED | K27: Minor ankle — precaution | L27: 🎯 R5 TARGET · INJURY: minor ankle (precaution). Minimal impact. | M27: ▲ Up
A28: {=IFERROR(INDEX('Draft Board'!$A$2:$A$179,MATCH($D28,'Draft Board'!$D$2:$D$179,0)),"☐")} -> ☐ | B28: 27 | C28: R5 | D28: Mike Evans | E28: 55 | F28: San Francisco 49ers | G28: 8 | H28: 53.8 | I28: -4 | J28: Fair | K28: Minor groin — plans to play Wk1 | L28: INJURY: groin ('minor'); plans to play Week 1. Solid WR2 if healthy. | M28: ▲ Up
A29: {=IFERROR(INDEX('Draft Board'!$A$2:$A$179,MATCH($D29,'Draft Board'!$D$2:$D$179,0)),"☐")} -> ☐ | B29: 28 | C29: R5 | D29: Christian Watson | E29: 57 | F29: Green Bay Packers | G29: 11 | H29: 56.3 | I29: -3 | J29: Fair | L29: Fairly valued vs the market. Target ~R5; don't reach much earlier. | M29: ▲ Up
A30: {=IFERROR(INDEX('Draft Board'!$A$2:$A$179,MATCH($D30,'Draft Board'!$D$2:$D$179,0)),"☐")} -> ☐ | B30: 29 | C30: R6 | D30: Courtland Sutton | E30: 61 | F30: Denver Broncos | G30: 10 | H30: 59.7 | I30: -18 | J30: OVERVALUED | L30: Market drafts him ~18 spots ahead of the Aug-9 expert board (ADP ~R5) — fade, or he's risen since. | M30: ▲ Up
A31: {=IFERROR(INDEX('Draft Board'!$A$2:$A$179,MATCH($D31,'Draft Board'!$D$2:$D$179,0)),"☐")} -> ☐ | B31: 30 | C31: R6 | D31: Luther Burden III | E31: 62 | F31: Chicago Bears | G31: 10 | H31: 61.7 | I31: +15 | J31: UNDERVALUED | K31: Groin — ~1 month, hopeful Wk1 | L31: 💤 SLEEPER — Ben Johnson offense + ~150 vacated targets; elite YAC — big breakout once healthy. INJURY: groin (Aug 8), out ~a month, hopeful for Week 1. Now WR2 behind Rome Odunze — risky at ADP. | M31: ▲ Up
A32: {=IFERROR(INDEX('Draft Board'!$A$2:$A$179,MATCH($D32,'Draft Board'!$D$2:$D$179,0)),"☐")} -> ☐ | B32: 31 | C32: R6 | D32: DK Metcalf | E32: 64 | F32: Pittsburgh Steelers | G32: 9 | H32: 63.3 | I32: -10 | J32: OVERVALUED | L32: Fairly valued vs the market. Target ~R6; don't reach much earlier. | M32: ▲ Up
A33: {=IFERROR(INDEX('Draft Board'!$A$2:$A$179,MATCH($D33,'Draft Board'!$D$2:$D$179,0)),"☐")} -> ☐ | B33: 32 | C33: R6 | D33: Marvin Harrison Jr. | E33: 65 | F33: Arizona Cardinals | G33: 14 | H33: 65 | I33: -3 | J33: Fair | L33: Fairly valued vs the market. Target ~R6; don't reach much earlier. | M33: ▲ Up
A34: {=IFERROR(INDEX('Draft Board'!$A$2:$A$179,MATCH($D34,'Draft Board'!$D$2:$D$179,0)),"☐")} -> ☐ | B34: 33 | C34: R6 | D34: Brian Thomas Jr. | E34: 68 | F34: Jacksonville Jaguars | G34: 7 | H34: 69.5 | I34: -2 | J34: Fair | L34: Fairly valued vs the market. Target ~R6; don't reach much earlier. | M34: ▲ Up
A35: {=IFERROR(INDEX('Draft Board'!$A$2:$A$179,MATCH($D35,'Draft Board'!$D$2:$D$179,0)),"☐")} -> ☐ | B35: 34 | C35: R6 | D35: Carnell Tate | E35: 71 | F35: Tennessee Titans | G35: 9 | H35: 73.9 | I35: +8 | J35: UNDERVALUED | L35: 💤 SLEEPER — pro-ready rookie, TEN's new go-to target. Fairly valued vs the market. Target ~R6; don't reach much earlier. | M35: ▲ Up
A36: {=IFERROR(INDEX('Draft Board'!$A$2:$A$179,MATCH($D36,'Draft Board'!$D$2:$D$179,0)),"☐")} -> ☐ | B36: 35 | C36: R7 | D36: Alec Pierce | E36: 74 | F36: Indianapolis Colts | G36: 13 | H36: 56.4 | I36: -22 | J36: OVERVALUED | K36: PUP ankle — back to practice soon | L36: 🎯 R6 TARGET · INJURY: on PUP (ankle surgery) but expected back at practice this week; targeting Week 1. Boom/bust WR2 — confirm active. | M36: ▲ Up
A37: {=IFERROR(INDEX('Draft Board'!$A$2:$A$179,MATCH($D37,'Draft Board'!$D$2:$D$179,0)),"☐")} -> ☐ | B37: 36 | C37: R7 | D37: Parker Washington | E37: 75 | F37: Jacksonville Jaguars | G37: 7 | H37: 64.7 | I37: -21 | J37: OVERVALUED | L37: 🎯 R7 TARGET · Riser — market ~R6 vs stale expert R8. | M37: ▲ Up
A38: {=IFERROR(INDEX('Draft Board'!$A$2:$A$179,MATCH($D38,'Draft Board'!$D$2:$D$179,0)),"☐")} -> ☐ | B38: 37 | C38: R8 | D38: Michael Wilson | E38: 85 | F38: Arizona Cardinals | G38: 14 | H38: 76.1 | I38: -20 | J38: OVERVALUED | L38: Riser — market ~R7 vs stale expert R9. | M38: ▲ Up
A39: {=IFERROR(INDEX('Draft Board'!$A$2:$A$179,MATCH($D39,'Draft Board'!$D$2:$D$179,0)),"☐")} -> ☐ | B39: 38 | C39: R8 | D39: Chris Godwin | E39: 86 | F39: Tampa Bay Buccaneers | G39: 10 | H39: 77.6 | I39: -14 | J39: OVERVALUED | L39: Market drafts him ~14 spots ahead of the Aug-9 expert board (ADP ~R7) — fade, or he's risen since. | M39: ▲ Up
A40: {=IFERROR(INDEX('Draft Board'!$A$2:$A$179,MATCH($D40,'Draft Board'!$D$2:$D$179,0)),"☐")} -> ☐ | B40: 39 | C40: R8 | D40: Michael Pittman Jr. | E40: 87 | F40: Pittsburgh Steelers | G40: 9 | H40: 81 | I40: -15 | J40: OVERVALUED | L40: Market drafts him ~15 spots ahead of the Aug-9 expert board (ADP ~R7) — fade, or he's risen since. | M40: ▲ Up
A41: {=IFERROR(INDEX('Draft Board'!$A$2:$A$179,MATCH($D41,'Draft Board'!$D$2:$D$179,0)),"☐")} -> ☐ | B41: 40 | C41: R8 | D41: Jakobi Meyers | E41: 88 | F41: Jacksonville Jaguars | G41: 7 | H41: 85.9 | I41: -6 | J41: OVERVALUED | L41: Fairly valued vs the market. Target ~R8; don't reach much earlier. | M41: ▲ Up
A42: {=IFERROR(INDEX('Draft Board'!$A$2:$A$179,MATCH($D42,'Draft Board'!$D$2:$D$179,0)),"☐")} -> ☐ | B42: 41 | C42: R8 | D42: Quentin Johnston | E42: 89 | F42: Los Angeles Chargers | G42: 7 | H42: 86.2 | I42: -8 | J42: OVERVALUED | L42: Fairly valued vs the market. Target ~R8; don't reach much earlier. | M42: ▲ Up
A43: {=IFERROR(INDEX('Draft Board'!$A$2:$A$179,MATCH($D43,'Draft Board'!$D$2:$D$179,0)),"☐")} -> ☐ | B43: 42 | C43: R8 | D43: Josh Downs | E43: 90 | F43: IND | G43: 13 | H43: 87.7 | I43: — | J43: Depth | K43: Calf — day-to-day | L43: 💤 SLEEPER — high-volume IND slot; PPR value, more if Pierce misses time. INJURY: calf, day-to-day. Slot value, especially if Pierce misses time. | M43: ▲ Up
A44: {=IFERROR(INDEX('Draft Board'!$A$2:$A$179,MATCH($D44,'Draft Board'!$D$2:$D$179,0)),"☐")} -> ☐ | B44: 43 | C44: R8 | D44: Jordan Addison | E44: 91 | F44: MIN | G44: 6 | H44: 88.1 | I44: — | J44: Depth | L44: MIN WR2; ADP ~R8. | M44: ▲ Up
A45: {=IFERROR(INDEX('Draft Board'!$A$2:$A$179,MATCH($D45,'Draft Board'!$D$2:$D$179,0)),"☐")} -> ☐ | B45: 44 | C45: R8 | D45: Jayden Reed | E45: 94 | F45: GB | G45: 11 | H45: 91.2 | I45: — | J45: Depth | L45: GB WR; volatile week to week. | M45: ▲ Up
A46: {=IFERROR(INDEX('Draft Board'!$A$2:$A$179,MATCH($D46,'Draft Board'!$D$2:$D$179,0)),"☐")} -> ☐ | B46: 45 | C46: R8 | D46: Wan'Dale Robinson | E46: 96 | F46: TEN | G46: 9 | H46: 93.2 | I46: — | J46: Depth | L46: 🎯 R8 TARGET · High-volume slot WR. | M46: ▲ Up
A47: {=IFERROR(INDEX('Draft Board'!$A$2:$A$179,MATCH($D47,'Draft Board'!$D$2:$D$179,0)),"☐")} -> ☐ | B47: 46 | C47: R8 | D47: Stefon Diggs | E47: 99 | F47: WAS | G47: 7 | H47: 94.2 | I47: — | J47: Depth | L47: 🎯 R9 TARGET · 💤 SLEEPER — starts opposite McLaurin in WAS; WR3 upside at a late ADP. Riser — starts opposite McLaurin in WAS; WR3 upside at a WR49-ish ADP. | M47: ▲ Up
A48: {=IFERROR(INDEX('Draft Board'!$A$2:$A$179,MATCH($D48,'Draft Board'!$D$2:$D$179,0)),"☐")} -> ☐ | B48: 47 | C48: R8 | D48: Makai Lemon | E48: 102 | F48: Philadelphia Eagles | G48: 10 | H48: 111.5 | I48: +6 | J48: UNDERVALUED | L48: Rookie WR; market ~R10. Upside stash. | M48: ▲ Up
A49: {=IFERROR(INDEX('Draft Board'!$A$2:$A$179,MATCH($D49,'Draft Board'!$D$2:$D$179,0)),"☐")} -> ☐ | B49: 48 | C49: R9 | D49: Xavier Worthy | E49: 107 | F49: KC | G49: 5 | H49: 100.1 | I49: — | J49: Depth | L49: Speed WR in KC; boom/bust. | M49: ▲ Up
A50: {=IFERROR(INDEX('Draft Board'!$A$2:$A$179,MATCH($D50,'Draft Board'!$D$2:$D$179,0)),"☐")} -> ☐ | B50: 49 | C50: R9 | D50: Matthew Golden | E50: 111 | F50: GB | G50: 11 | H50: 102.2 | I50: — | J50: Depth | L50: Rookie WR, GB; upside flier. | M50: ▲ Up
A51: {=IFERROR(INDEX('Draft Board'!$A$2:$A$179,MATCH($D51,'Draft Board'!$D$2:$D$179,0)),"☐")} -> ☐ | B51: 50 | C51: R9 | D51: Deebo Samuel Sr. | E51: 116 | F51: SF | G51: 8 | H51: 106.4 | I51: — | J51: Depth | L51: Flex/upside in SF. | M51: ▲ Up
A52: {=IFERROR(INDEX('Draft Board'!$A$2:$A$179,MATCH($D52,'Draft Board'!$D$2:$D$179,0)),"☐")} -> ☐ | B52: 51 | C52: R9 | D52: Khalil Shakir | E52: 117 | F52: BUF | G52: 7 | H52: 106.7 | I52: — | J52: Depth | L52: Bills' slot target leader. | M52: ▲ Up
A53: {=IFERROR(INDEX('Draft Board'!$A$2:$A$179,MATCH($D53,'Draft Board'!$D$2:$D$179,0)),"☐")} -> ☐ | B53: 52 | C53: R9 | D53: Romeo Doubs | E53: 118 | F53: NE | G53: 11 | H53: 108 | I53: — | J53: Depth | L53: Depth WR (NE). | M53: ▲ Up
A54: {=IFERROR(INDEX('Draft Board'!$A$2:$A$179,MATCH($D54,'Draft Board'!$D$2:$D$179,0)),"☐")} -> ☐ | B54: 53 | C54: R9 | D54: Jordyn Tyson | E54: 121 | F54: New Orleans Saints | G54: 8 | H54: 126.9 | I54: +19 | J54: UNDERVALUED | K54: Hamstring — may linger to ~Wk7 | L54: 🎯 R10 TARGET · INJURY: hamstring, may linger to ~Week 7. Late-round dart only; Chris Olave benefits. | M54: ▲ Up
A55: {=IFERROR(INDEX('Draft Board'!$A$2:$A$179,MATCH($D55,'Draft Board'!$D$2:$D$179,0)),"☐")} -> ☐ | B55: 54 | C55: R10 | D55: KC Concepcion | E55: 126 | F55: CLE | G55: 11 | H55: 117.4 | I55: — | J55: Depth | L55: 🎯 R11 TARGET · Rookie WR upside. | M55: ▲ Up
A56: {=IFERROR(INDEX('Draft Board'!$A$2:$A$179,MATCH($D56,'Draft Board'!$D$2:$D$179,0)),"☐")} -> ☐ | B56: 55 | C56: R10 | D56: Jalen Coker | E56: 127 | F56: CAR | G56: 5 | H56: 117.5 | I56: — | J56: Depth | L56: 🎯 R11 TARGET · 💤 SLEEPER — ascending CAR WR; sleeper target share. CAR WR sleeper. | M56: ▲ Up
A57: {=IFERROR(INDEX('Draft Board'!$A$2:$A$179,MATCH($D57,'Draft Board'!$D$2:$D$179,0)),"☐")} -> ☐ | B57: 56 | C57: R10 | D57: Rashid Shaheed | E57: 128 | F57: SEA | G57: 11 | H57: 119.4 | I57: — | J57: Depth | L57: Deep threat; boom/bust. | M57: ▲ Up
A58: {=IFERROR(INDEX('Draft Board'!$A$2:$A$179,MATCH($D58,'Draft Board'!$D$2:$D$179,0)),"☐")} -> ☐ | B58: 57 | C58: R11 | D58: Jerry Jeudy | E58: 130 | F58: CLE | G58: 11 | H58: 125.4 | I58: — | J58: Depth | L58: CLE WR1; QB-dependent. | M58: ▲ Up
A59: {=IFERROR(INDEX('Draft Board'!$A$2:$A$179,MATCH($D59,'Draft Board'!$D$2:$D$179,0)),"☐")} -> ☐ | B59: 58 | C59: R11 | D59: Jayden Higgins | E59: 131 | F59: HOU | G59: 8 | H59: 127.1 | I59: — | J59: Depth | K59: Out for season (ACL) | L59: INJURY: torn ACL — out for the season. Do not draft. | M59: ▲ Up
A60: {=IFERROR(INDEX('Draft Board'!$A$2:$A$179,MATCH($D60,'Draft Board'!$D$2:$D$179,0)),"☐")} -> ☐ | B60: 59 | C60: R12 | D60: Keenan Allen | E60: 137 | F60: IND | G60: 13 | H60: 132.2 | I60: — | J60: Depth | L60: 🎯 R12 TARGET · Vet slot WR; PPR floor. | M60: ▲ Up
A61: {=IFERROR(INDEX('Draft Board'!$A$2:$A$179,MATCH($D61,'Draft Board'!$D$2:$D$179,0)),"☐")} -> ☐ | B61: 60 | C61: R12 | D61: Tre Tucker | E61: 139 | F61: LV | G61: 13 | H61: 132.4 | I61: — | J61: Depth | L61: LV deep threat. | M61: ▲ Up
A62: {=IFERROR(INDEX('Draft Board'!$A$2:$A$179,MATCH($D62,'Draft Board'!$D$2:$D$179,0)),"☐")} -> ☐ | B62: 61 | C62: R12 | D62: De'Zhaun Stribling | E62: 140 | F62: SF | G62: 8 | H62: 133.5 | I62: — | J62: Depth | L62: 🎯 R12 TARGET · Rookie WR, opportunity in SF. | M62: ▲ Up
A63: {=IFERROR(INDEX('Draft Board'!$A$2:$A$179,MATCH($D63,'Draft Board'!$D$2:$D$179,0)),"☐")} -> ☐ | B63: 62 | C63: R12 | D63: Rashod Bateman | E63: 142 | F63: BAL | G63: 13 | H63: 133.6 | I63: — | J63: Depth | L63: BAL WR; TD-dependent. | M63: ▲ Up
A64: {=IFERROR(INDEX('Draft Board'!$A$2:$A$179,MATCH($D64,'Draft Board'!$D$2:$D$179,0)),"☐")} -> ☐ | B64: 63 | C64: R12 | D64: Jalen McMillan | E64: 145 | F64: TB | G64: 10 | H64: 136 | I64: — | J64: Depth | L64: 🎯 R12 TARGET · TB WR sleeper. | M64: ▲ Up
A65: {=IFERROR(INDEX('Draft Board'!$A$2:$A$179,MATCH($D65,'Draft Board'!$D$2:$D$179,0)),"☐")} -> ☐ | B65: 64 | C65: R12 | D65: Calvin Ridley | E65: 146 | F65: TEN | G65: 9 | H65: 137.2 | I65: — | J65: Depth | L65: 🎯 R12 TARGET · TEN WR1; volume play. | M65: ▲ Up
A66: {=IFERROR(INDEX('Draft Board'!$A$2:$A$179,MATCH($D66,'Draft Board'!$D$2:$D$179,0)),"☐")} -> ☐ | B66: 65 | C66: R12 | D66: Jauan Jennings | E66: 148 | F66: MIN | G66: 6 | H66: 138.9 | I66: — | J66: Depth | L66: 🎯 R13 TARGET · MIN depth WR. | M66: ▲ Up
A67: {=IFERROR(INDEX('Draft Board'!$A$2:$A$179,MATCH($D67,'Draft Board'!$D$2:$D$179,0)),"☐")} -> ☐ | B67: 66 | C67: R12 | D67: Denzel Boston | E67: 153 | F67: CLE | G67: 11 | H67: 140.3 | I67: — | J67: Depth | L67: Rookie WR flier. | M67: ▲ Up
A68: {=IFERROR(INDEX('Draft Board'!$A$2:$A$179,MATCH($D68,'Draft Board'!$D$2:$D$179,0)),"☐")} -> ☐ | B68: 67 | C68: R13 | D68: Jalen Nailor | E68: 156 | F68: LV | G68: 13 | H68: 144.5 | I68: — | J68: Depth | L68: LV depth WR. | M68: ▲ Up
A69: {=IFERROR(INDEX('Draft Board'!$A$2:$A$179,MATCH($D69,'Draft Board'!$D$2:$D$179,0)),"☐")} -> ☐ | B69: 68 | C69: R13 | D69: Malik Washington | E69: 162 | F69: MIA | G69: 6 | H69: 148.5 | I69: — | J69: Depth | L69: MIA slot sleeper. | M69: ▲ Up
A70: {=IFERROR(INDEX('Draft Board'!$A$2:$A$179,MATCH($D70,'Draft Board'!$D$2:$D$179,0)),"☐")} -> ☐ | B70: 69 | C70: R13 | D70: Tank Dell | E70: 170 | F70: HOU | G70: 8 | H70: 155 | I70: — | J70: Depth | K70: Returning from 2025 knee reconstruction | L70: INJURY: returning from 2025 knee reconstruction. Monitor availability; upside flier. | M70: ▲ Up
A71: {=IFERROR(INDEX('Draft Board'!$A$2:$A$179,MATCH($D71,'Draft Board'!$D$2:$D$179,0)),"☐")} -> ☐ | B71: 70 | C71: R13 | D71: Cooper Kupp | E71: 171 | F71: SEA | G71: 11 | H71: 155.3 | I71: — | J71: Depth | L71: With SEA now; PPR floor if healthy. | M71: ▲ Up

Sheet QB
A1: Drafted | B1: Pos Rk | C1: Rec Rd | D1: Player | E1: Ovr | F1: Team | G1: Bye | H1: ADP | I1: Value | J1: Verdict | K1: Flag | L1: Notes | M1: PPR Lean
A2: {=IFERROR(INDEX('Draft Board'!$A$2:$A$179,MATCH($D2,'Draft Board'!$D$2:$D$179,0)),"☐")} -> ☐ | B2: 1 | C2: R3 | D2: Josh Allen | E2: 31 | F2: Buffalo Bills | G2: 7 | H2: 32.9 | I2: +8 | J2: UNDERVALUED | L2: Fairly valued vs the market. Target ~R3; don't reach much earlier. | M2: =
A3: {=IFERROR(INDEX('Draft Board'!$A$2:$A$179,MATCH($D3,'Draft Board'!$D$2:$D$179,0)),"☐")} -> ☐ | B3: 2 | C3: R4 | D3: Lamar Jackson | E3: 46 | F3: Baltimore Ravens | G3: 13 | H3: 56.7 | I3: +22 | J3: UNDERVALUED | L3: Experts' QB2; market waits ~R5. Wait-on-QB reward. | M3: =
A4: {=IFERROR(INDEX('Draft Board'!$A$2:$A$179,MATCH($D4,'Draft Board'!$D$2:$D$179,0)),"☐")} -> ☐ | B4: 3 | C4: R5 | D4: Drake Maye | E4: 53 | F4: New England Patriots | G4: 11 | H4: 51.9 | I4: +2 | J4: Fair | L4: 🎯 R5 TARGET · Fairly valued vs the market. Target ~R5; don't reach much earlier. | M4: =
A5: {=IFERROR(INDEX('Draft Board'!$A$2:$A$179,MATCH($D5,'Draft Board'!$D$2:$D$179,0)),"☐")} -> ☐ | B5: 4 | C5: R5 | D5: Joe Burrow | E5: 58 | F5: Cincinnati Bengals | G5: 6 | H5: 56.4 | I5: +2 | J5: Fair | L5: Fairly valued vs the market. Target ~R5; don't reach much earlier. | M5: =
A6: {=IFERROR(INDEX('Draft Board'!$A$2:$A$179,MATCH($D6,'Draft Board'!$D$2:$D$179,0)),"☐")} -> ☐ | B6: 5 | C6: R6 | D6: Jayden Daniels | E6: 70 | F6: Washington Commanders | G6: 7 | H6: 71 | I6: +10 | J6: UNDERVALUED | L6: Experts rank him ~10 spots above the market (ADP ~R6). QB value if you trust the board. | M6: =
A7: {=IFERROR(INDEX('Draft Board'!$A$2:$A$179,MATCH($D7,'Draft Board'!$D$2:$D$179,0)),"☐")} -> ☐ | B7: 6 | C7: R6 | D7: Jalen Hurts | E7: 73 | F7: Philadelphia Eagles | G7: 10 | H7: 80.9 | I7: +18 | J7: UNDERVALUED | L7: 🎯 R6 TARGET · Experts' QB5; market ~R7. Rushing-floor QB at a discount. | M7: =
A8: {=IFERROR(INDEX('Draft Board'!$A$2:$A$179,MATCH($D8,'Draft Board'!$D$2:$D$179,0)),"☐")} -> ☐ | B8: 7 | C8: R7 | D8: Dak Prescott | E8: 76 | F8: Dallas Cowboys | G8: 14 | H8: 65.5 | I8: -11 | J8: OVERVALUED | L8: 🎯 R7 TARGET · Fairly valued vs the market. Target ~R7; don't reach much earlier. | M8: =
A9: {=IFERROR(INDEX('Draft Board'!$A$2:$A$179,MATCH($D9,'Draft Board'!$D$2:$D$179,0)),"☐")} -> ☐ | B9: 8 | C9: R7 | D9: Matthew Stafford | E9: 79 | F9: LAR | G9: 11 | H9: 78.3 | I9: — | J9: Depth | L9: QB in a strong passing offense; ~R7 streamer. | M9: =
A10: {=IFERROR(INDEX('Draft Board'!$A$2:$A$179,MATCH($D10,'Draft Board'!$D$2:$D$179,0)),"☐")} -> ☐ | B10: 9 | C10: R8 | D10: Brock Purdy | E10: 92 | F10: SF | G10: 8 | H10: 88.4 | I10: — | J10: Depth | L10: Streaming QB. | M10: =
A11: {=IFERROR(INDEX('Draft Board'!$A$2:$A$179,MATCH($D11,'Draft Board'!$D$2:$D$179,0)),"☐")} -> ☐ | B11: 10 | C11: R8 | D11: Caleb Williams | E11: 93 | F11: Chicago Bears | G11: 10 | H11: 91 | I11: +5 | J11: Fair | L11: Fairly valued vs the market. Target ~R8; don't reach much earlier. | M11: =
A12: {=IFERROR(INDEX('Draft Board'!$A$2:$A$179,MATCH($D12,'Draft Board'!$D$2:$D$179,0)),"☐")} -> ☐ | B12: 11 | C12: R8 | D12: Trevor Lawrence | E12: 100 | F12: Jacksonville Jaguars | G12: 7 | H12: 95.6 | I12: -2 | J12: Fair | L12: 🎯 R9 TARGET · Fairly valued vs the market. Target ~R8; don't reach much earlier. | M12: =
A13: {=IFERROR(INDEX('Draft Board'!$A$2:$A$179,MATCH($D13,'Draft Board'!$D$2:$D$179,0)),"☐")} -> ☐ | B13: 12 | C13: R8 | D13: Justin Herbert | E13: 101 | F13: Los Angeles Chargers | G13: 7 | H13: 109.7 | I13: +6 | J13: UNDERVALUED | L13: 🎯 R9 TARGET · Late QB value (~R10). | M13: =
... A22: {=IFERROR(INDEX('Draft Board'!$A$2:$A$179,MATCH($D22,'Draft Board'!$D$2:$D$179,0)),"☐")} -> ☐ | B22: 21 | C22: R13 | D22: Jordan Love | E22: 167 | F22: GB | G22: 11 | H22: 151.8 | I22: — | J22: Depth | L22: Falls in 1-QB; solid streaming QB2. | M22: =

Sheet TE
A1: Drafted | B1: Pos Rk | C1: Rec Rd | D1: Player | E1: Ovr | F1: Team | G1: Bye | H1: ADP | I1: Value | J1: Verdict | K1: Flag | L1: Notes | M1: PPR Lean
A2: {=IFERROR(INDEX('Draft Board'!$A$2:$A$179,MATCH($D2,'Draft Board'!$D$2:$D$179,0)),"☐")} -> ☐ | B2: 1 | C2: R3 | D2: Trey McBride | E2: 34 | F2: Arizona Cardinals | G2: 14 | H2: 38.2 | I2: +17 | J2: UNDERVALUED | L2: Experts' TE2; market ~R4. Second shot at the premium-TE tier. | M2: ▲ Up
A3: {=IFERROR(INDEX('Draft Board'!$A$2:$A$179,MATCH($D3,'Draft Board'!$D$2:$D$179,0)),"☐")} -> ☐ | B3: 2 | C3: R3 | D3: Brock Bowers | E3: 35 | F3: Las Vegas Raiders | G3: 13 | H3: 43 | I3: +24 | J3: UNDERVALUED | L3: Experts' TE1, ranked well above where the market drafts him (~R4). Elite TE edge if you want it. | M3: ▲ Up
A4: {=IFERROR(INDEX('Draft Board'!$A$2:$A$179,MATCH($D4,'Draft Board'!$D$2:$D$179,0)),"☐")} -> ☐ | B4: 3 | C4: R5 | D4: Colston Loveland | E4: 60 | F4: Chicago Bears | G4: 10 | H4: 61.3 | I4: +21 | J4: UNDERVALUED | L4: Experts high on this rookie TE (TE3); market ~R6. Rookie variance. | M4: ▲ Up
A5: {=IFERROR(INDEX('Draft Board'!$A$2:$A$179,MATCH($D5,'Draft Board'!$D$2:$D$179,0)),"☐")} -> ☐ | B5: 4 | C5: R6 | D5: Tyler Warren | E5: 69 | F5: Indianapolis Colts | G5: 13 | H5: 70.4 | I5: +15 | J5: UNDERVALUED | K5: Adductor — minor; Wk1 not in jeopardy | L5: [Sep 3] Adductor strain confirmed minor; Wk1 is not in serious jeopardy. 💤 SLEEPER — elite projected TE volume in IND; breakout (monitor adductor). INJURY: adductor strain (~1 week); Week 1 not in serious jeopardy. Minimal draft impact. | M5: ▲ Up
A6: {=IFERROR(INDEX('Draft Board'!$A$2:$A$179,MATCH($D6,'Draft Board'!$D$2:$D$179,0)),"☐")} -> ☐ | B6: 5 | C6: R7 | D6: Harold Fannin Jr. | E6: 82 | F6: Cleveland Browns | G6: 11 | H6: 83.8 | I6: +14 | J6: UNDERVALUED | L6: Deep-sleeper rookie TE; experts TE5, market ~R7. | M6: ▲ Up
A7: {=IFERROR(INDEX('Draft Board'!$A$2:$A$179,MATCH($D7,'Draft Board'!$D$2:$D$179,0)),"☐")} -> ☐ | B7: 6 | C7: R7 | D7: Kyle Pitts | E7: 83 | F7: Atlanta Falcons | G7: 11 | H7: 85.2 | I7: +7 | J7: UNDERVALUED | L7: Fairly valued vs the market. Target ~R7; don't reach much earlier. | M7: ▲ Up
A8: {=IFERROR(INDEX('Draft Board'!$A$2:$A$179,MATCH($D8,'Draft Board'!$D$2:$D$179,0)),"☐")} -> ☐ | B8: 7 | C8: R7 | D8: Tucker Kraft | E8: 84 | F8: Green Bay Packers | G8: 11 | H8: 100.5 | I8: +17 | J8: UNDERVALUED | L8: Value TE (experts' TE5-6); market ~R9. No injury reported. | M8: ▲ Up
A9: {=IFERROR(INDEX('Draft Board'!$A$2:$A$179,MATCH($D9,'Draft Board'!$D$2:$D$179,0)),"☐")} -> ☐ | B9: 8 | C9: R8 | D9: Sam LaPorta | E9: 98 | F9: Detroit Lions | G9: 6 | H9: 94.2 | I9: +5 | J9: Fair | L9: 🎯 R8 TARGET · Bounce-back TE; market ~R8. | M9: ▲ Up
A10: {=IFERROR(INDEX('Draft Board'!$A$2:$A$179,MATCH($D10,'Draft Board'!$D$2:$D$179,0)),"☐")} -> ☐ | B10: 9 | C10: R9 | D10: Dallas Goedert | E10: 113 | F10: PHI | G10: 10 | H10: 104 | I10: — | J10: Depth | L10: Streaming TE. | M10: ▲ Up
A11: {=IFERROR(INDEX('Draft Board'!$A$2:$A$179,MATCH($D11,'Draft Board'!$D$2:$D$179,0)),"☐")} -> ☐ | B11: 10 | C11: R9 | D11: George Kittle | E11: 119 | F11: San Francisco 49ers | G11: 8 | H11: 117.6 | I11: -2 | J11: Fair | K11: Off PUP — targeting Wk1 (may ease in) | L11: [Sep 3] Activated off PUP; 49ers are confident for Wk1 though he may ease in early. Achilles recovery on track — clear upgrade from the summer PUP outlook. INJURY: torn Achilles (2025 playoffs), on PUP — Week 1 in doubt. Downgrade until he practices; stream Jake Tonges if he sits. | M11: ▲ Up
A12: {=IFERROR(INDEX('Draft Board'!$A$2:$A$179,MATCH($D12,'Draft Board'!$D$2:$D$179,0)),"☐")} -> ☐ | B12: 11 | C12: R9 | D12: Travis Kelce | E12: 120 | F12: Kansas City Chiefs | G12: 5 | H12: 122.5 | I12: 0 | J12: Fair | L12: 🎯 R10 TARGET · Falls on age; still a featured Chiefs role. | M12: ▲ Up
A13: {=IFERROR(INDEX('Draft Board'!$A$2:$A$179,MATCH($D13,'Draft Board'!$D$2:$D$179,0)),"☐")} -> ☐ | B13: 12 | C13: R12 | D13: Mark Andrews | E13: 136 | F13: BAL | G13: 13 | H13: 132.1 | I13: — | J13: Depth | L13: Streaming TE; TD-dependent. | M13: ▲ Up
A14: {=IFERROR(INDEX('Draft Board'!$A$2:$A$179,MATCH($D14,'Draft Board'!$D$2:$D$179,0)),"☐")} -> ☐ | B14: 13 | C14: R12 | D14: Isaiah Likely | E14: 143 | F14: NYG | G14: 8 | H14: 135.2 | I14: — | J14: Depth | L14: 💤 SLEEPER — every-down TE role in NYG; streaming-plus upside. Moved to NYG; streaming TE. | M14: ▲ Up
A15: {=IFERROR(INDEX('Draft Board'!$A$2:$A$179,MATCH($D15,'Draft Board'!$D$2:$D$179,0)),"☐")} -> ☐ | B15: 14 | C15: R13 | D15: Jake Ferguson | E15: 158 | F15: DAL | G15: 14 | H15: 145.3 | I15: — | J15: Depth | L15: DAL streaming TE. | M15: ▲ Up
A16: {=IFERROR(INDEX('Draft Board'!$A$2:$A$179,MATCH($D16,'Draft Board'!$D$2:$D$179,0)),"☐")} -> ☐ | B16: 15 | C16: R13 | D16: Dalton Kincaid | E16: 169 | F16: BUF | G16: 7 | H16: 153.8 | I16: — | J16: Depth | L16: BUF streaming TE. | M16: ▲ Up

Sheet K & DST
A1: Kickers & Defenses (D/ST) — top options by ADP. ESPN scoring: see notes below and the 'ESPN Scoring' tab.
A2: ESPN K scoring is distance-based (FG 0-39=3, 40-49=4, 50-59=5, 60+=6; PAT=1) and penalizes misses (missed FG -1, missed PAT -2) — so target accurate, strong-legged kickers in high-scoring offenses (Aubrey holds #1). ESPN D/ST scoring is generous but swingy (+1/sack, +2 per takeaway/safety, +6 def TDs, plus points- AND yards-allowed tiers down to -7). TARGET a top-5 D/ST around R7-8 and a top-3 K around R11 rather than waiting to the final rounds; a top unit locks in a Week-1 edge. Highlighted = units to prioritize. NEWS (Sep 3): Aaron Donald has come out of retirement to rejoin the Rams — a boost to the LA Rams D/ST.
A4: KICKERS
A5: Rank | B5: Rd | C5: Kicker | D5: Team | E5: Bye | F5: ADP
A6: 1 | B6: R11 | C6: Brandon Aubrey | D6: DAL | E6: 14 | F6: 131.5
A7: 2 | B7: R12 | C7: Ka'imi Fairbairn | D7: HOU | E7: 8 | F7: 133.5
A8: 3 | B8: R12 | C8: Jason Myers | D8: SEA | E8: 11 | F8: 141.5
A9: 4 | B9: R13 | C9: Cameron Dicker | D9: LAC | E9: 7 | F9: 144.8
A10: 5 | B10: R13 | C10: Chase McLaughlin | D10: TB | E10: 10 | F10: 145.6
A11: 6 | B11: R13 | C11: Tyler Loop | D11: BAL | E11: 13 | F11: 147.1
A12: 7 | B12: R13 | C12: Cam Little | D12: JAX | E12: 7 | F12: 150.1
A13: 8 | B13: R13 | C13: Harrison Mevis | D13: LAR | E13: 11 | F13: 150.7
A14: 9 | B14: R13 | C14: Jake Bates | D14: DET | E14: 6 | F14: 150.7
A15: 10 | B15: R14 | C15: Wil Lutz | D15: DEN | E15: 10 | F15: 161.9
A17: DEFENSES (D/ST)
A18: Rank | B18: Rd | C18: Defense | D18: Team | E18: Bye | F18: ADP
A19: 1 | B19: R7 | C19: Seattle | D19: SEA | E19: 11 | F19: 81.8
A20: 2 | B20: R8 | C20: Denver | D20: DEN | E20: 10 | F20: 91.2
A21: 3 | B21: R9 | C21: Houston | D21: HOU | E21: 8 | F21: 101.7
A22: 4 | B22: R10 | C22: Minnesota | D22: MIN | E22: 6 | F22: 108.6
A23: 5 | B23: R10 | C23: LA Rams | D23: LAR | E23: 11 | F23: 112.3
A24: 6 | B24: R11 | C24: New England | D24: NE | E24: 11 | F24: 129.5
A25: 7 | B25: R11 | C25: Pittsburgh | D25: PIT | E25: 9 | F25: 131.9
A26: 8 | B26: R12 | C26: Detroit | D26: DET | E26: 6 | F26: 132.3
A27: 9 | B27: R12 | C27: Philadelphia | D27: PHI | E27: 10 | F27: 139.9
A28: 10 | B28: R12 | C28: LA Chargers | D28: LAC | E28: 7 | F28: 142.8
A29: 11 | B29: R14 | C29: Jacksonville | D29: JAX | E29: 7 | F29: 159.8
A30: 12 | B30: R14 | C30: Buffalo | D30: BUF | E30: 7 | F30: 160.6

Sheet _AllData
A1: Name | B1: Pos | C1: Team | D1: Bye | E1: Flag
A2: Jahmyr Gibbs | B2: RB | C2: Detroit Lions | D2: 6
A3: Bijan Robinson | B3: RB | C3: Atlanta Falcons | D3: 11
A4: Puka Nacua | B4: WR | C4: Los Angeles Rams | D4: 11 | E4: Not on exempt list (Sep 1) — likely Wk1; small lingering risk
A5: Ja'Marr Chase | B5: WR | C5: Cincinnati Bengals | D5: 6
A6: Jaxon Smith-Njigba | B6: WR | C6: Seattle Seahawks | D6: 11
A7: Jonathan Taylor | B7: RB | C7: Indianapolis Colts | D7: 13
A8: Christian McCaffrey | B8: RB | C8: San Francisco 49ers | D8: 8 | E8: Back to full practice — Wk1 expected (age/workload watch)
A9: Amon-Ra St. Brown | B9: WR | C9: Detroit Lions | D9: 6
A10: James Cook | B10: RB | C10: Buffalo Bills | D10: 7
A11: Derrick Henry | B11: RB | C11: Baltimore Ravens | D11: 13
A12: De'Von Achane | B12: RB | C12: Miami Dolphins | D12: 6
A13: Drake London | B13: WR | C13: Atlanta Falcons | D13: 11
A14: CeeDee Lamb | B14: WR | C14: Dallas Cowboys | D14: 14
A15: Justin Jefferson | B15: WR | C15: Minnesota Vikings | D15: 6
A16: Ashton Jeanty | B16: RB | C16: Las Vegas Raiders | D16: 13 | E16: Ankle — made 53-man, no return date; monitor
A17: Chase Brown | B17: RB | C17: Cincinnati Bengals | D17: 6
A18: Rashee Rice | B18: WR | C18: Kansas City Chiefs | D18: 5 | E18: CLEARED — NFL closed investigation (Apr 2026), no discipline
A19: Saquon Barkley | B19: RB | C19: Philadelphia Eagles | D19: 10
A20: A.J. Brown | B20: WR | C20: New England Patriots | D20: 11
A21: George Pickens | B21: WR | C21: Dallas Cowboys | D21: 14
A22: Nico Collins | B22: WR | C22: Houston Texans | D22: 8
A23: Kenneth Walker III | B23: RB | C23: Kansas City Chiefs | D23: 5
A24: Omarion Hampton | B24: RB | C24: Los Angeles Chargers | D24: 7
A25: Chris Olave | B25: WR | C25: New Orleans Saints | D25: 8
A26: Josh Jacobs | B26: RB | C26: Green Bay Packers | D26: 11 | E26: ON COMMISSIONER'S EXEMPT LIST (Aug 30) — out indefinitely
A27: Zay Flowers | B27: WR | C27: Baltimore Ravens | D27: 13
A28: Kyren Williams | B28: RB | C28: Los Angeles Rams | D28: 11
A29: Malik Nabers | B29: WR | C29: New York Giants | D29: 8 | E29: Post-ACL — ramping to Wk1, top-10 upside
A30: Jeremiyah Love | B30: RB | C30: Arizona Cardinals | D30: 14 | E30: High ankle sprain — ~50/50 for Wk1
A31: Garrett Wilson | B31: WR | C31: New York Jets | D31: 13
A32: DeVonta Smith | B32: WR | C32: Philadelphia Eagles | D32: 10
A33: Tetairoa McMillan | B33: WR | C33: Carolina Panthers | D33: 5
A34: Josh Allen | B34: QB | C34: Buffalo Bills | D34: 7
A35: Javonte Williams | B35: RB | C35: Dallas Cowboys | D35: 14
A36: Cam Skattebo | B36: RB | C36: New York Giants | D36: 8
A37: Breece Hall | B37: RB | C37: New York Jets | D37: 13 | E37: Groin — ~2-3 weeks
A38: Emeka Egbuka | B38: WR | C38: Tampa Bay Buccaneers | D38: 10 | E38: Toe — Wk1 status uncertain
A39: Tee Higgins | B39: WR | C39: Cincinnati Bengals | D39: 6
A40: Trey McBride | B40: TE | C40: Arizona Cardinals | D40: 14
A41: Davante Adams | B41: WR | C41: Los Angeles Rams | D41: 11
A42: Travis Etienne Jr. | B42: RB | C42: New Orleans Saints | D42: 8
A43: Jameson Williams | B43: WR | C43: Detroit Lions | D43: 6
A44: Ladd McConkey | B44: WR | C44: Los Angeles Chargers | D44: 7
A45: Brock Bowers | B45: TE | C45: Las Vegas Raiders | D45: 13
A46: D'Andre Swift | B46: RB | C46: Chicago Bears | D46: 10 | E46: Bigger role — Monangai (knee) out weeks
A47: Terry McLaurin | B47: WR | C47: Washington Commanders | D47: 7
A48: Bucky Irving | B48: RB | C48: Tampa Bay Buccaneers | D48: 10
A49: Rome Odunze | B49: WR | C49: Chicago Bears | D49: 10
A50: Jaylen Waddle | B50: WR | C50: Denver Broncos | D50: 10
A51: D.J. Moore | B51: WR | C51: Buffalo Bills | D51: 7 | E51: Minor ankle — precaution
A52: Quinshon Judkins | B52: RB | C52: Cleveland Browns | D52: 11
A53: Drake Maye | B53: QB | C53: New England Patriots | D53: 11
A54: Bhayshul Tuten | B54: RB | C54: Jacksonville Jaguars | D54: 7
A55: Mike Evans | B55: WR | C55: San Francisco 49ers | D55: 8 | E55: Minor groin — plans to play Wk1
A56: David Montgomery | B56: RB | C56: Houston Texans | D56: 8
A57: Christian Watson | B57: WR | C57: Green Bay Packers | D57: 11
A58: Joe Burrow | B58: QB | C58: Cincinnati Bengals | D58: 6
A59: Alec Pierce | B59: WR | C59: Indianapolis Colts | D59: 13 | E59: PUP ankle — back to practice soon
A60: Lamar Jackson | B60: QB | C60: Baltimore Ravens | D60: 13
A61: Courtland Sutton | B61: WR | C61: Denver Broncos | D61: 10
A62: TreVeyon Henderson | B62: RB | C62: New England Patriots | D62: 11
A63: Colston Loveland | B63: TE | C63: Chicago Bears | D63: 10
A64: Luther Burden III | B64: WR | C64: Chicago Bears | D64: 10 | E64: Groin — ~1 month, hopeful Wk1
A65: Jaylen Warren | B65: RB | C65: Pittsburgh Steelers | D65: 9
A66: DK Metcalf | B66: WR | C66: Pittsburgh Steelers | D66: 9
A67: Parker Washington | B67: WR | C67: Jacksonville Jaguars | D67: 7
A68: Marvin Harrison Jr. | B68: WR | C68: Arizona Cardinals | D68: 14
A69: Dak Prescott | B69: QB | C69: Dallas Cowboys | D69: 14
A70: Tony Pollard | B70: RB | C70: Tennessee Titans | D70: 9
A71: Rhamondre Stevenson | B71: RB | C71: New England Patriots | D71: 11
A72: Brian Thomas Jr. | B72: WR | C72: Jacksonville Jaguars | D72: 7
A73: Tyler Warren | B73: TE | C73: Indianapolis Colts | D73: 13 | E73: Adductor — minor; Wk1 not in jeopardy
A74: Jayden Daniels | B74: QB | C74: Washington Commanders | D74: 7
A75: Carnell Tate | B75: WR | C75: Tennessee Titans | D75: 9
A76: Rico Dowdle | B76: RB | C76: Pittsburgh Steelers | D76: 9
A77: Jadarian Price | B77: RB | C77: Seattle Seahawks | D77: 11 | E77: SEA lead back — Charbonnet (IR) out ~4 wks
A78: Michael Wilson | B78: WR | C78: Arizona Cardinals | D78: 14
A79: Chuba Hubbard | B79: RB | C79: Carolina Panthers | D79: 5 | E79: Hamstring — committee w/ Brooks
A80: Chris Godwin | B80: WR | C80: Tampa Bay Buccaneers | D80: 10
A81: Jalen Hurts | B81: QB | C81: Philadelphia Eagles | D81: 10
A82: Michael Pittman Jr. | B82: WR | C82: Pittsburgh Steelers | D82: 9
A83: J.K. Dobbins | B83: RB | C83: Denver Broncos | D83: 10 | E83: Soft-tissue — may start slow
A84: Harold Fannin Jr. | B84: TE | C84: Cleveland Browns | D84: 11
A85: Kyle Pitts | B85: TE | C85: Atlanta Falcons | D85: 11
A86: Jakobi Meyers | B86: WR | C86: Jacksonville Jaguars | D86: 7
A87: Quentin Johnston | B87: WR | C87: Los Angeles Chargers | D87: 7
A88: Caleb Williams | B88: QB | C88: Chicago Bears | D88: 10
A89: RJ Harvey | B89: RB | C89: Denver Broncos | D89: 10
A90: Sam LaPorta | B90: TE | C90: Detroit Lions | D90: 6
A91: Trevor Lawrence | B91: QB | C91: Jacksonville Jaguars | D91: 7
A92: Tucker Kraft | B92: TE | C92: Green Bay Packers | D92: 11
A93: Kyle Monangai | B93: RB | C93: Chicago Bears | D93: 10 | E93: Hyperextended knee — out multiple weeks; Wk1 in doubt
A94: Patrick Mahomes | B94: QB | C94: Kansas City Chiefs | D94: 5
A95: Justin Herbert | B95: QB | C95: Los Angeles Chargers | D95: 7
A96: Makai Lemon | B96: WR | C96: Philadelphia Eagles | D96: 10
A97: George Kittle | B97: TE | C97: San Francisco 49ers | D97: 8 | E97: Off PUP — targeting Wk1 (may ease in)
A98: Blake Corum | B98: RB | C98: Los Angeles Rams | D98: 11
A99: Jaxson Dart | B99: QB | C99: New York Giants | D99: 8
A100: Travis Kelce | B100: TE | C100: Kansas City Chiefs | D100: 5
...
